<?xml version="1.0"?>
<Info xmlns:xsd="http://www.w3.org/2001/XMLSchema" xmlns:xsi="http://www.w3.org/2001/XMLSchema-instance">
  <CreationDate>2006-06-29T15:13:27.1875000+01:00</CreationDate>
  <Comments>Created by the XML Converter Plugin</Comments>
  <Document>
    <FileName>C:\Program Files\Common Files\Logitech\io2SoftwareSdk\PenFiles\IS1000a.pen_3.pen</FileName>
    <Subject>C:\Program Files\Common Files\Logitech\io2SoftwareSdk\PenFiles\IS1000a.pen_3.pen</Subject>
    <Layer>
      <StartDate>2004-10-28T09:12:08.0000000+01:00</StartDate>
      <EndDate>2004-10-28T09:16:34.0000000+01:00</EndDate>
      <Duration>4</Duration>
      <StrokeCount>68</StrokeCount>
      <PageNum>1</PageNum>
      <Stroke>
        <StrokeIdx>0</StrokeIdx>
        <ID>0</ID>
        <StartDate>2004-10-28T09:12:08.0000000+01:00</StartDate>
        <StartMs>343</StartMs>
        <Duration>1066</Duration>
        <Color>-14090101</Color>
        <Width>1</Width>
        <Points>
          <X>86.25</X>
          <Y>31.875</Y>
        </Points>
        <Points>
          <X>83.125</X>
          <Y>45</Y>
        </Points>
        <Points>
          <X>82.75</X>
          <Y>46.625</Y>
        </Points>
        <Points>
          <X>82.75</X>
          <Y>47.75</Y>
        </Points>
        <Points>
          <X>82.75</X>
          <Y>48</Y>
        </Points>
        <Points>
          <X>82.75</X>
          <Y>48</Y>
        </Points>
        <Points>
          <X>82.75</X>
          <Y>48</Y>
        </Points>
        <Points>
          <X>87.125</X>
          <Y>35.5</Y>
        </Points>
        <Points>
          <X>88</X>
          <Y>30.625</Y>
        </Points>
        <Points>
          <X>88</X>
          <Y>29.875</Y>
        </Points>
        <Points>
          <X>84.125</X>
          <Y>46.875</Y>
        </Points>
        <Points>
          <X>83.75</X>
          <Y>48.5</Y>
        </Points>
        <Points>
          <X>84.375</X>
          <Y>43.625</Y>
        </Points>
        <Points>
          <X>86.625</X>
          <Y>34.875</Y>
        </Points>
        <Points>
          <X>86.125</X>
          <Y>38.875</Y>
        </Points>
        <Points>
          <X>83.375</X>
          <Y>48.75</Y>
        </Points>
        <Points>
          <X>83.375</X>
          <Y>48.875</Y>
        </Points>
        <Points>
          <X>83.25</X>
          <Y>48.875</Y>
        </Points>
        <Points>
          <X>82.75</X>
          <Y>48.5</Y>
        </Points>
        <Forces>00:1E:1E:1E:20:1E:1E:18:1E:30:48:48:4C:50:52:56:54:48:00:</Forces>
      </Stroke>
      <Stroke>
        <StrokeIdx>1</StrokeIdx>
        <ID>1</ID>
        <StartDate>2004-10-28T09:12:10.0000000+01:00</StartDate>
        <StartMs>69</StartMs>
        <Duration>560</Duration>
        <Color>-14090101</Color>
        <Width>1</Width>
        <Points>
          <X>85.25</X>
          <Y>26.125</Y>
        </Points>
        <Points>
          <X>85.625</X>
          <Y>24.625</Y>
        </Points>
        <Points>
          <X>85.75</X>
          <Y>24.625</Y>
        </Points>
        <Points>
          <X>86.25</X>
          <Y>28.5</Y>
        </Points>
        <Points>
          <X>85</X>
          <Y>37.75</Y>
        </Points>
        <Points>
          <X>83.5</X>
          <Y>48.75</Y>
        </Points>
        <Points>
          <X>86.5</X>
          <Y>27.5</Y>
        </Points>
        <Points>
          <X>81.625</X>
          <Y>42.75</Y>
        </Points>
        <Points>
          <X>81.25</X>
          <Y>44</Y>
        </Points>
        <Points>
          <X>81</X>
          <Y>44.5</Y>
        </Points>
        <Points>
          <X>80.625</X>
          <Y>44.875</Y>
        </Points>
        <Points>
          <X>80.25</X>
          <Y>44.875</Y>
        </Points>
        <Forces>00:20:26:46:54:58:5A:5E:5C:50:2E:00:</Forces>
      </Stroke>
      <Stroke>
        <StrokeIdx>2</StrokeIdx>
        <ID>2</ID>
        <StartDate>2004-10-28T09:12:11.0000000+01:00</StartDate>
        <StartMs>-230</StartMs>
        <Duration>253</Duration>
        <Color>-14090101</Color>
        <Width>1</Width>
        <Points>
          <X>90.375</X>
          <Y>28</Y>
        </Points>
        <Points>
          <X>90.625</X>
          <Y>26.875</Y>
        </Points>
        <Points>
          <X>91.125</X>
          <Y>26.25</Y>
        </Points>
        <Points>
          <X>91.75</X>
          <Y>26</Y>
        </Points>
        <Points>
          <X>92.5</X>
          <Y>26.25</Y>
        </Points>
        <Points>
          <X>93.625</X>
          <Y>26.875</Y>
        </Points>
        <Points>
          <X>95</X>
          <Y>29.125</Y>
        </Points>
        <Points>
          <X>95.75</X>
          <Y>33.5</Y>
        </Points>
        <Points>
          <X>94.625</X>
          <Y>39</Y>
        </Points>
        <Points>
          <X>91.625</X>
          <Y>44.375</Y>
        </Points>
        <Points>
          <X>89.75</X>
          <Y>46.125</Y>
        </Points>
        <Points>
          <X>87.125</X>
          <Y>48.125</Y>
        </Points>
        <Points>
          <X>84.625</X>
          <Y>49.75</Y>
        </Points>
        <Points>
          <X>83.25</X>
          <Y>50.375</Y>
        </Points>
        <Points>
          <X>82.375</X>
          <Y>50.5</Y>
        </Points>
        <Forces>00:0C:14:38:3C:42:4A:52:56:5A:5A:58:50:38:00:</Forces>
      </Stroke>
      <Stroke>
        <StrokeIdx>3</StrokeIdx>
        <ID>3</ID>
        <StartDate>2004-10-28T09:12:11.0000000+01:00</StartDate>
        <StartMs>198</StartMs>
        <Duration>240</Duration>
        <Color>-14090101</Color>
        <Width>1</Width>
        <Points>
          <X>80.25</X>
          <Y>24</Y>
        </Points>
        <Points>
          <X>79.25</X>
          <Y>23</Y>
        </Points>
        <Points>
          <X>78.75</X>
          <Y>22.875</Y>
        </Points>
        <Points>
          <X>78.25</X>
          <Y>23.25</Y>
        </Points>
        <Points>
          <X>77.375</X>
          <Y>24.5</Y>
        </Points>
        <Points>
          <X>74.75</X>
          <Y>30.375</Y>
        </Points>
        <Points>
          <X>73.375</X>
          <Y>34</Y>
        </Points>
        <Points>
          <X>71.375</X>
          <Y>40.5</Y>
        </Points>
        <Points>
          <X>70.375</X>
          <Y>46.625</Y>
        </Points>
        <Points>
          <X>71.25</X>
          <Y>50</Y>
        </Points>
        <Points>
          <X>73.125</X>
          <Y>51.875</Y>
        </Points>
        <Points>
          <X>74.875</X>
          <Y>52.25</Y>
        </Points>
        <Points>
          <X>79.625</X>
          <Y>51.25</Y>
        </Points>
        <Forces>00:12:16:2C:38:48:4C:50:54:54:50:4A:00:</Forces>
      </Stroke>
      <Stroke>
        <StrokeIdx>4</StrokeIdx>
        <ID>4</ID>
        <StartDate>2004-10-28T09:12:17.0000000+01:00</StartDate>
        <StartMs>-202</StartMs>
        <Duration>386</Duration>
        <Color>-14090101</Color>
        <Width>1</Width>
        <Points>
          <X>138.125</X>
          <Y>31.75</Y>
        </Points>
        <Points>
          <X>138</X>
          <Y>30.75</Y>
        </Points>
        <Points>
          <X>138</X>
          <Y>30.5</Y>
        </Points>
        <Points>
          <X>137.875</X>
          <Y>30.5</Y>
        </Points>
        <Points>
          <X>137.25</X>
          <Y>31.375</Y>
        </Points>
        <Points>
          <X>136.125</X>
          <Y>32.75</Y>
        </Points>
        <Points>
          <X>133</X>
          <Y>37</Y>
        </Points>
        <Points>
          <X>130.875</X>
          <Y>41.125</Y>
        </Points>
        <Points>
          <X>130</X>
          <Y>45.25</Y>
        </Points>
        <Points>
          <X>131.625</X>
          <Y>47.375</Y>
        </Points>
        <Points>
          <X>132.875</X>
          <Y>47.75</Y>
        </Points>
        <Points>
          <X>134.375</X>
          <Y>47.375</Y>
        </Points>
        <Points>
          <X>138.75</X>
          <Y>44.375</Y>
        </Points>
        <Points>
          <X>142.25</X>
          <Y>39.625</Y>
        </Points>
        <Points>
          <X>143.125</X>
          <Y>37</Y>
        </Points>
        <Points>
          <X>143</X>
          <Y>34.625</Y>
        </Points>
        <Points>
          <X>140.625</X>
          <Y>31.625</Y>
        </Points>
        <Points>
          <X>139.25</X>
          <Y>30.75</Y>
        </Points>
        <Points>
          <X>137.75</X>
          <Y>30.375</Y>
        </Points>
        <Points>
          <X>137</X>
          <Y>30.375</Y>
        </Points>
        <Points>
          <X>136.625</X>
          <Y>30.875</Y>
        </Points>
        <Forces>00:00:08:1A:2C:30:34:36:36:32:30:2E:2E:2C:2E:2E:34:32:2C:18:00:</Forces>
      </Stroke>
      <Stroke>
        <StrokeIdx>5</StrokeIdx>
        <ID>5</ID>
        <StartDate>2004-10-28T09:12:17.0000000+01:00</StartDate>
        <StartMs>298</StartMs>
        <Duration>306</Duration>
        <Color>-14090101</Color>
        <Width>1</Width>
        <Points>
          <X>148.375</X>
          <Y>35</Y>
        </Points>
        <Points>
          <X>146.5</X>
          <Y>39.25</Y>
        </Points>
        <Points>
          <X>146.375</X>
          <Y>39.75</Y>
        </Points>
        <Points>
          <X>150.625</X>
          <Y>36</Y>
        </Points>
        <Points>
          <X>153</X>
          <Y>35</Y>
        </Points>
        <Points>
          <X>153.5</X>
          <Y>35.375</Y>
        </Points>
        <Points>
          <X>153.625</X>
          <Y>36</Y>
        </Points>
        <Points>
          <X>153.5</X>
          <Y>38.625</Y>
        </Points>
        <Points>
          <X>153.5</X>
          <Y>41.125</Y>
        </Points>
        <Points>
          <X>153.75</X>
          <Y>41.875</Y>
        </Points>
        <Points>
          <X>154.25</X>
          <Y>42.5</Y>
        </Points>
        <Forces>00:26:28:2C:30:34:38:42:3A:16:00:</Forces>
      </Stroke>
      <Stroke>
        <StrokeIdx>6</StrokeIdx>
        <ID>6</ID>
        <StartDate>2004-10-28T09:12:18.0000000+01:00</StartDate>
        <StartMs>-293</StartMs>
        <Duration>106</Duration>
        <Color>-14090101</Color>
        <Width>1</Width>
        <Points>
          <X>161.875</X>
          <Y>38.875</Y>
        </Points>
        <Points>
          <X>162.625</X>
          <Y>38.625</Y>
        </Points>
        <Points>
          <X>165.75</X>
          <Y>38.125</Y>
        </Points>
        <Points>
          <X>170</X>
          <Y>37.375</Y>
        </Points>
        <Points>
          <X>171.625</X>
          <Y>37</Y>
        </Points>
        <Forces>00:32:36:28:00:</Forces>
      </Stroke>
      <Stroke>
        <StrokeIdx>7</StrokeIdx>
        <ID>7</ID>
        <StartDate>2004-10-28T09:12:18.0000000+01:00</StartDate>
        <StartMs>18</StartMs>
        <Duration>653</Duration>
        <Color>-14090101</Color>
        <Width>1</Width>
        <Points>
          <X>190</X>
          <Y>33.5</Y>
        </Points>
        <Points>
          <X>189.625</X>
          <Y>32.375</Y>
        </Points>
        <Points>
          <X>189.25</X>
          <Y>31.875</Y>
        </Points>
        <Points>
          <X>188.375</X>
          <Y>31.375</Y>
        </Points>
        <Points>
          <X>187.5</X>
          <Y>32</Y>
        </Points>
        <Points>
          <X>186.875</X>
          <Y>33</Y>
        </Points>
        <Points>
          <X>185.75</X>
          <Y>36.25</Y>
        </Points>
        <Points>
          <X>185.875</X>
          <Y>38.5</Y>
        </Points>
        <Points>
          <X>186.375</X>
          <Y>39</Y>
        </Points>
        <Points>
          <X>187.125</X>
          <Y>39.125</Y>
        </Points>
        <Points>
          <X>188</X>
          <Y>38.75</Y>
        </Points>
        <Points>
          <X>189</X>
          <Y>37.75</Y>
        </Points>
        <Points>
          <X>193.25</X>
          <Y>26.375</Y>
        </Points>
        <Points>
          <X>195.375</X>
          <Y>23</Y>
        </Points>
        <Points>
          <X>197.5</X>
          <Y>20.625</Y>
        </Points>
        <Points>
          <X>200</X>
          <Y>18.75</Y>
        </Points>
        <Points>
          <X>200.875</X>
          <Y>18.75</Y>
        </Points>
        <Points>
          <X>201.375</X>
          <Y>19.125</Y>
        </Points>
        <Points>
          <X>201.875</X>
          <Y>20.25</Y>
        </Points>
        <Points>
          <X>202.125</X>
          <Y>22.375</Y>
        </Points>
        <Points>
          <X>200.875</X>
          <Y>28.25</Y>
        </Points>
        <Points>
          <X>190.875</X>
          <Y>51.375</Y>
        </Points>
        <Points>
          <X>188.375</X>
          <Y>56.75</Y>
        </Points>
        <Points>
          <X>185.125</X>
          <Y>66</Y>
        </Points>
        <Points>
          <X>184.25</X>
          <Y>69.625</Y>
        </Points>
        <Points>
          <X>184.125</X>
          <Y>71.875</Y>
        </Points>
        <Points>
          <X>184.625</X>
          <Y>72.875</Y>
        </Points>
        <Points>
          <X>185.125</X>
          <Y>73</Y>
        </Points>
        <Points>
          <X>186.25</X>
          <Y>72.25</Y>
        </Points>
        <Points>
          <X>188.25</X>
          <Y>70.25</Y>
        </Points>
        <Points>
          <X>190</X>
          <Y>67.375</Y>
        </Points>
        <Points>
          <X>191.5</X>
          <Y>63.5</Y>
        </Points>
        <Points>
          <X>192.625</X>
          <Y>59</Y>
        </Points>
        <Points>
          <X>193.5</X>
          <Y>52.25</Y>
        </Points>
        <Forces>00:00:0C:38:3C:3C:3C:3A:34:28:28:28:2A:28:2A:2C:30:32:34:3A:42:4A:48:48:46:46:3E:3A:38:38:3C:3A:34:00:</Forces>
      </Stroke>
      <Stroke>
        <StrokeIdx>8</StrokeIdx>
        <ID>8</ID>
        <StartDate>2004-10-28T09:12:19.0000000+01:00</StartDate>
        <StartMs>-168</StartMs>
        <Duration>320</Duration>
        <Color>-14090101</Color>
        <Width>1</Width>
        <Points>
          <X>210.5</X>
          <Y>26</Y>
        </Points>
        <Points>
          <X>209.875</X>
          <Y>25.25</Y>
        </Points>
        <Points>
          <X>209.5</X>
          <Y>25.875</Y>
        </Points>
        <Points>
          <X>209</X>
          <Y>27.125</Y>
        </Points>
        <Points>
          <X>200.5</X>
          <Y>55.625</Y>
        </Points>
        <Points>
          <X>199.5</X>
          <Y>59.375</Y>
        </Points>
        <Points>
          <X>199.25</X>
          <Y>62.25</Y>
        </Points>
        <Points>
          <X>199.5</X>
          <Y>63.75</Y>
        </Points>
        <Points>
          <X>199.875</X>
          <Y>64</Y>
        </Points>
        <Points>
          <X>201.625</X>
          <Y>62.875</Y>
        </Points>
        <Points>
          <X>204.375</X>
          <Y>58.375</Y>
        </Points>
        <Points>
          <X>206.125</X>
          <Y>51.5</Y>
        </Points>
        <Points>
          <X>206.25</X>
          <Y>48.375</Y>
        </Points>
        <Points>
          <X>206.125</X>
          <Y>44.625</Y>
        </Points>
        <Forces>00:20:32:36:40:3E:3E:3C:34:36:3A:38:34:00:</Forces>
      </Stroke>
      <Stroke>
        <StrokeIdx>9</StrokeIdx>
        <ID>9</ID>
        <StartDate>2004-10-28T09:12:19.0000000+01:00</StartDate>
        <StartMs>350</StartMs>
        <Duration>346</Duration>
        <Color>-14090101</Color>
        <Width>1</Width>
        <Points>
          <X>243.375</X>
          <Y>26.375</Y>
        </Points>
        <Points>
          <X>242.125</X>
          <Y>25.125</Y>
        </Points>
        <Points>
          <X>241.25</X>
          <Y>25.25</Y>
        </Points>
        <Points>
          <X>240.5</X>
          <Y>26.375</Y>
        </Points>
        <Points>
          <X>236.5</X>
          <Y>37.625</Y>
        </Points>
        <Points>
          <X>234.5</X>
          <Y>41.625</Y>
        </Points>
        <Points>
          <X>234.875</X>
          <Y>40.75</Y>
        </Points>
        <Points>
          <X>235.875</X>
          <Y>39.375</Y>
        </Points>
        <Points>
          <X>237.625</X>
          <Y>37.875</Y>
        </Points>
        <Points>
          <X>240</X>
          <Y>37</Y>
        </Points>
        <Points>
          <X>242</X>
          <Y>36.75</Y>
        </Points>
        <Points>
          <X>243.125</X>
          <Y>37.125</Y>
        </Points>
        <Points>
          <X>243.625</X>
          <Y>39.125</Y>
        </Points>
        <Points>
          <X>243.125</X>
          <Y>40.25</Y>
        </Points>
        <Points>
          <X>241</X>
          <Y>41.875</Y>
        </Points>
        <Points>
          <X>239</X>
          <Y>42.5</Y>
        </Points>
        <Points>
          <X>235.5</X>
          <Y>43.125</Y>
        </Points>
        <Forces>00:2C:28:2C:34:36:3C:3A:34:34:34:34:36:3A:40:3E:0E:</Forces>
      </Stroke>
      <Stroke>
        <StrokeIdx>10</StrokeIdx>
        <ID>10</ID>
        <StartDate>2004-10-28T09:12:20.0000000+01:00</StartDate>
        <StartMs>-182</StartMs>
        <Duration>186</Duration>
        <Color>-14090101</Color>
        <Width>1</Width>
        <Points>
          <X>248.75</X>
          <Y>38.5</Y>
        </Points>
        <Points>
          <X>248.25</X>
          <Y>39</Y>
        </Points>
        <Points>
          <X>248</X>
          <Y>39.75</Y>
        </Points>
        <Points>
          <X>248.25</X>
          <Y>42</Y>
        </Points>
        <Points>
          <X>248.875</X>
          <Y>43.25</Y>
        </Points>
        <Points>
          <X>249.875</X>
          <Y>43.875</Y>
        </Points>
        <Points>
          <X>252.25</X>
          <Y>43.625</Y>
        </Points>
        <Points>
          <X>254.625</X>
          <Y>41.375</Y>
        </Points>
        <Points>
          <X>255.625</X>
          <Y>37.75</Y>
        </Points>
        <Points>
          <X>256.375</X>
          <Y>35.75</Y>
        </Points>
        <Forces>00:14:22:26:28:2A:36:3A:28:00:</Forces>
      </Stroke>
      <Stroke>
        <StrokeIdx>11</StrokeIdx>
        <ID>11</ID>
        <StartDate>2004-10-28T09:12:20.0000000+01:00</StartDate>
        <StartMs>109</StartMs>
        <Duration>173</Duration>
        <Color>-14090101</Color>
        <Width>1</Width>
        <Points>
          <X>266.375</X>
          <Y>23.625</Y>
        </Points>
        <Points>
          <X>266.5</X>
          <Y>24.125</Y>
        </Points>
        <Points>
          <X>266.375</X>
          <Y>25.75</Y>
        </Points>
        <Points>
          <X>266</X>
          <Y>28.25</Y>
        </Points>
        <Points>
          <X>265.5</X>
          <Y>31.375</Y>
        </Points>
        <Points>
          <X>263.625</X>
          <Y>36.875</Y>
        </Points>
        <Points>
          <X>262</X>
          <Y>42</Y>
        </Points>
        <Points>
          <X>261.75</X>
          <Y>43.5</Y>
        </Points>
        <Points>
          <X>262.125</X>
          <Y>44</Y>
        </Points>
        <Forces>00:42:44:46:46:46:3C:12:00:</Forces>
      </Stroke>
      <Stroke>
        <StrokeIdx>12</StrokeIdx>
        <ID>12</ID>
        <StartDate>2004-10-28T09:12:20.0000000+01:00</StartDate>
        <StartMs>382</StartMs>
        <Duration>133</Duration>
        <Color>-14090101</Color>
        <Width>1</Width>
        <Points>
          <X>272.125</X>
          <Y>28.875</Y>
        </Points>
        <Points>
          <X>271.75</X>
          <Y>28.125</Y>
        </Points>
        <Points>
          <X>271.5</X>
          <Y>27.75</Y>
        </Points>
        <Points>
          <X>271.375</X>
          <Y>27.75</Y>
        </Points>
        <Points>
          <X>271.5</X>
          <Y>28.875</Y>
        </Points>
        <Points>
          <X>271.625</X>
          <Y>33</Y>
        </Points>
        <Points>
          <X>271.375</X>
          <Y>35.25</Y>
        </Points>
        <Points>
          <X>271.125</X>
          <Y>37</Y>
        </Points>
        <Points>
          <X>270.25</X>
          <Y>38.5</Y>
        </Points>
        <Forces>00:00:20:38:40:3C:26:00:00:</Forces>
      </Stroke>
      <Stroke>
        <StrokeIdx>13</StrokeIdx>
        <ID>13</ID>
        <StartDate>2004-10-28T09:12:21.0000000+01:00</StartDate>
        <StartMs>-404</StartMs>
        <Duration>413</Duration>
        <Color>-14090101</Color>
        <Width>1</Width>
        <Points>
          <X>259.625</X>
          <Y>36.625</Y>
        </Points>
        <Points>
          <X>259.625</X>
          <Y>35.125</Y>
        </Points>
        <Points>
          <X>260.375</X>
          <Y>34.25</Y>
        </Points>
        <Points>
          <X>263.75</X>
          <Y>33.125</Y>
        </Points>
        <Points>
          <X>270.5</X>
          <Y>32.625</Y>
        </Points>
        <Points>
          <X>278.25</X>
          <Y>33.5</Y>
        </Points>
        <Points>
          <X>279.125</X>
          <Y>33.875</Y>
        </Points>
        <Points>
          <X>279.375</X>
          <Y>34.375</Y>
        </Points>
        <Points>
          <X>279.25</X>
          <Y>34.875</Y>
        </Points>
        <Points>
          <X>278.125</X>
          <Y>36.375</Y>
        </Points>
        <Points>
          <X>277.5</X>
          <Y>37.375</Y>
        </Points>
        <Points>
          <X>276.375</X>
          <Y>41</Y>
        </Points>
        <Points>
          <X>276.625</X>
          <Y>42</Y>
        </Points>
        <Points>
          <X>277.125</X>
          <Y>42.625</Y>
        </Points>
        <Points>
          <X>277.875</X>
          <Y>42.75</Y>
        </Points>
        <Points>
          <X>278.625</X>
          <Y>42.5</Y>
        </Points>
        <Points>
          <X>279.5</X>
          <Y>41.875</Y>
        </Points>
        <Points>
          <X>280.5</X>
          <Y>39.625</Y>
        </Points>
        <Points>
          <X>280.625</X>
          <Y>37.75</Y>
        </Points>
        <Points>
          <X>280.5</X>
          <Y>36</Y>
        </Points>
        <Points>
          <X>280.125</X>
          <Y>34.625</Y>
        </Points>
        <Points>
          <X>279.75</X>
          <Y>33.875</Y>
        </Points>
        <Points>
          <X>279.375</X>
          <Y>34</Y>
        </Points>
        <Forces>00:00:00:04:00:02:08:1A:30:3E:40:3E:3E:3A:36:36:38:40:42:40:40:3E:00:</Forces>
      </Stroke>
      <Stroke>
        <StrokeIdx>14</StrokeIdx>
        <ID>14</ID>
        <StartDate>2004-10-28T09:12:21.0000000+01:00</StartDate>
        <StartMs>148</StartMs>
        <Duration>386</Duration>
        <Color>-14090101</Color>
        <Width>1</Width>
        <Points>
          <X>288</X>
          <Y>38.375</Y>
        </Points>
        <Points>
          <X>287.25</X>
          <Y>39</Y>
        </Points>
        <Points>
          <X>287.125</X>
          <Y>39.75</Y>
        </Points>
        <Points>
          <X>286.25</X>
          <Y>43</Y>
        </Points>
        <Points>
          <X>287.75</X>
          <Y>40.5</Y>
        </Points>
        <Points>
          <X>293.125</X>
          <Y>37.75</Y>
        </Points>
        <Points>
          <X>294.125</X>
          <Y>37.625</Y>
        </Points>
        <Points>
          <X>294.5</X>
          <Y>37.75</Y>
        </Points>
        <Points>
          <X>295</X>
          <Y>40.625</Y>
        </Points>
        <Points>
          <X>295.25</X>
          <Y>40.875</Y>
        </Points>
        <Points>
          <X>297.375</X>
          <Y>41</Y>
        </Points>
        <Points>
          <X>299</X>
          <Y>40.5</Y>
        </Points>
        <Forces>00:36:3C:3E:46:46:48:48:4E:4E:4C:44:</Forces>
      </Stroke>
      <Stroke>
        <StrokeIdx>15</StrokeIdx>
        <ID>15</ID>
        <StartDate>2004-10-28T09:12:24.0000000+01:00</StartDate>
        <StartMs>-145</StartMs>
        <Duration>653</Duration>
        <Color>-14090101</Color>
        <Width>1</Width>
        <Points>
          <X>66.625</X>
          <Y>91</Y>
        </Points>
        <Points>
          <X>66</X>
          <Y>90.25</Y>
        </Points>
        <Points>
          <X>66.125</X>
          <Y>90</Y>
        </Points>
        <Points>
          <X>66.125</X>
          <Y>89.625</Y>
        </Points>
        <Points>
          <X>66.375</X>
          <Y>89.125</Y>
        </Points>
        <Points>
          <X>66.625</X>
          <Y>88.625</Y>
        </Points>
        <Points>
          <X>67</X>
          <Y>88</Y>
        </Points>
        <Points>
          <X>70.375</X>
          <Y>85.625</Y>
        </Points>
        <Points>
          <X>71.125</X>
          <Y>85.5</Y>
        </Points>
        <Points>
          <X>72.625</X>
          <Y>87.125</Y>
        </Points>
        <Points>
          <X>72.5</X>
          <Y>89.625</Y>
        </Points>
        <Points>
          <X>70.875</X>
          <Y>93.375</Y>
        </Points>
        <Points>
          <X>68.75</X>
          <Y>96.25</Y>
        </Points>
        <Points>
          <X>66.5</X>
          <Y>98.25</Y>
        </Points>
        <Points>
          <X>63.375</X>
          <Y>100</Y>
        </Points>
        <Points>
          <X>63.375</X>
          <Y>99.75</Y>
        </Points>
        <Points>
          <X>63.625</X>
          <Y>99.5</Y>
        </Points>
        <Points>
          <X>64.125</X>
          <Y>99</Y>
        </Points>
        <Points>
          <X>65</X>
          <Y>98.375</Y>
        </Points>
        <Points>
          <X>67</X>
          <Y>97.875</Y>
        </Points>
        <Points>
          <X>70.5</X>
          <Y>100.125</Y>
        </Points>
        <Points>
          <X>70.875</X>
          <Y>100.125</Y>
        </Points>
        <Points>
          <X>71.5</X>
          <Y>99.75</Y>
        </Points>
        <Points>
          <X>71.875</X>
          <Y>99</Y>
        </Points>
        <Forces>00:16:22:24:26:2A:2C:2C:2C:2E:32:34:36:3A:3C:40:3E:3C:3E:3E:3E:3C:0C:00:</Forces>
      </Stroke>
      <Stroke>
        <StrokeIdx>16</StrokeIdx>
        <ID>16</ID>
        <StartDate>2004-10-28T09:12:25.0000000+01:00</StartDate>
        <StartMs>-343</StartMs>
        <Duration>613</Duration>
        <Color>-14090101</Color>
        <Width>1</Width>
        <Points>
          <X>74.875</X>
          <Y>84</Y>
        </Points>
        <Points>
          <X>73.25</X>
          <Y>81.875</Y>
        </Points>
        <Points>
          <X>72.125</X>
          <Y>80.25</Y>
        </Points>
        <Points>
          <X>71.625</X>
          <Y>79.875</Y>
        </Points>
        <Points>
          <X>71</X>
          <Y>79.875</Y>
        </Points>
        <Points>
          <X>67.25</X>
          <Y>82</Y>
        </Points>
        <Points>
          <X>62.625</X>
          <Y>87.25</Y>
        </Points>
        <Points>
          <X>59.875</X>
          <Y>92.125</Y>
        </Points>
        <Points>
          <X>58.375</X>
          <Y>96.875</Y>
        </Points>
        <Points>
          <X>58.5</X>
          <Y>101.125</Y>
        </Points>
        <Points>
          <X>59.625</X>
          <Y>104.625</Y>
        </Points>
        <Points>
          <X>61.75</X>
          <Y>106.875</Y>
        </Points>
        <Points>
          <X>63.125</X>
          <Y>107.5</Y>
        </Points>
        <Points>
          <X>67.125</X>
          <Y>107.125</Y>
        </Points>
        <Points>
          <X>71.875</X>
          <Y>104.875</Y>
        </Points>
        <Points>
          <X>75.625</X>
          <Y>102.125</Y>
        </Points>
        <Points>
          <X>77</X>
          <Y>100.5</Y>
        </Points>
        <Points>
          <X>77.875</X>
          <Y>98.75</Y>
        </Points>
        <Points>
          <X>78.875</X>
          <Y>94</Y>
        </Points>
        <Points>
          <X>78.5</X>
          <Y>86</Y>
        </Points>
        <Points>
          <X>77.875</X>
          <Y>84.125</Y>
        </Points>
        <Points>
          <X>75.75</X>
          <Y>81.75</Y>
        </Points>
        <Points>
          <X>73.75</X>
          <Y>80.625</Y>
        </Points>
        <Points>
          <X>73.125</X>
          <Y>80.625</Y>
        </Points>
        <Points>
          <X>72.5</X>
          <Y>80.75</Y>
        </Points>
        <Points>
          <X>72.5</X>
          <Y>80.75</Y>
        </Points>
        <Points>
          <X>72.5</X>
          <Y>80.75</Y>
        </Points>
        <Points>
          <X>72.5</X>
          <Y>80.75</Y>
        </Points>
        <Forces>00:00:24:30:38:3A:40:42:42:42:42:42:40:40:40:40:40:40:42:44:46:50:4E:4E:4A:46:34:02:</Forces>
      </Stroke>
      <Stroke>
        <StrokeIdx>17</StrokeIdx>
        <ID>17</ID>
        <StartDate>2004-10-28T09:14:47.0000000+01:00</StartDate>
        <StartMs>-349</StartMs>
        <Duration>160</Duration>
        <Color>-14090101</Color>
        <Width>1</Width>
        <Points>
          <X>138.875</X>
          <Y>87.75</Y>
        </Points>
        <Points>
          <X>133.5</X>
          <Y>100.75</Y>
        </Points>
        <Forces>00:00:</Forces>
      </Stroke>
      <Stroke>
        <StrokeIdx>18</StrokeIdx>
        <ID>18</ID>
        <StartDate>2004-10-28T09:14:47.0000000+01:00</StartDate>
        <StartMs>21</StartMs>
        <Duration>453</Duration>
        <Color>-14090101</Color>
        <Width>1</Width>
        <Points>
          <X>139.75</X>
          <Y>88.125</Y>
        </Points>
        <Points>
          <X>142.375</X>
          <Y>86.5</Y>
        </Points>
        <Points>
          <X>147.5</X>
          <Y>84.625</Y>
        </Points>
        <Points>
          <X>148.25</X>
          <Y>84.75</Y>
        </Points>
        <Points>
          <X>148.875</X>
          <Y>85.5</Y>
        </Points>
        <Points>
          <X>149.125</X>
          <Y>86.75</Y>
        </Points>
        <Points>
          <X>149</X>
          <Y>88.375</Y>
        </Points>
        <Points>
          <X>147.875</X>
          <Y>90.5</Y>
        </Points>
        <Points>
          <X>145.875</X>
          <Y>93.125</Y>
        </Points>
        <Points>
          <X>142.25</X>
          <Y>96</Y>
        </Points>
        <Points>
          <X>145.375</X>
          <Y>94.75</Y>
        </Points>
        <Points>
          <X>146.5</X>
          <Y>94.625</Y>
        </Points>
        <Points>
          <X>147.125</X>
          <Y>95.125</Y>
        </Points>
        <Points>
          <X>147.875</X>
          <Y>97.375</Y>
        </Points>
        <Points>
          <X>147.75</X>
          <Y>98.75</Y>
        </Points>
        <Points>
          <X>147</X>
          <Y>100.125</Y>
        </Points>
        <Points>
          <X>145.75</X>
          <Y>101</Y>
        </Points>
        <Points>
          <X>142.5</X>
          <Y>101.625</Y>
        </Points>
        <Points>
          <X>141.625</X>
          <Y>101.5</Y>
        </Points>
        <Points>
          <X>141.125</X>
          <Y>101.125</Y>
        </Points>
        <Points>
          <X>140.75</X>
          <Y>100.75</Y>
        </Points>
        <Points>
          <X>140.625</X>
          <Y>100.25</Y>
        </Points>
        <Points>
          <X>140.875</X>
          <Y>100</Y>
        </Points>
        <Forces>00:00:00:00:00:00:00:00:00:00:00:00:00:00:00:00:02:1C:2A:30:30:14:00:</Forces>
      </Stroke>
      <Stroke>
        <StrokeIdx>19</StrokeIdx>
        <ID>19</ID>
        <StartDate>2004-10-28T09:14:48.0000000+01:00</StartDate>
        <StartMs>-374</StartMs>
        <Duration>333</Duration>
        <Color>-14090101</Color>
        <Width>1</Width>
        <Points>
          <X>162.625</X>
          <Y>92.25</Y>
        </Points>
        <Points>
          <X>160.875</X>
          <Y>93.25</Y>
        </Points>
        <Points>
          <X>156.625</X>
          <Y>101</Y>
        </Points>
        <Points>
          <X>156.75</X>
          <Y>100.125</Y>
        </Points>
        <Points>
          <X>157.5</X>
          <Y>97.5</Y>
        </Points>
        <Points>
          <X>159.375</X>
          <Y>94.5</Y>
        </Points>
        <Points>
          <X>163</X>
          <Y>90</Y>
        </Points>
        <Points>
          <X>164.875</X>
          <Y>89</Y>
        </Points>
        <Points>
          <X>166.5</X>
          <Y>91</Y>
        </Points>
        <Points>
          <X>167.25</X>
          <Y>94.125</Y>
        </Points>
        <Points>
          <X>166.625</X>
          <Y>97.75</Y>
        </Points>
        <Forces>00:24:2C:40:38:36:36:36:2E:2C:00:</Forces>
      </Stroke>
      <Stroke>
        <StrokeIdx>20</StrokeIdx>
        <ID>20</ID>
        <StartDate>2004-10-28T09:14:48.0000000+01:00</StartDate>
        <StartMs>67</StartMs>
        <Duration>53</Duration>
        <Color>-14090101</Color>
        <Width>1</Width>
        <Points>
          <X>160</X>
          <Y>96.25</Y>
        </Points>
        <Points>
          <X>160</X>
          <Y>95.625</Y>
        </Points>
        <Points>
          <X>161</X>
          <Y>95.125</Y>
        </Points>
        <Points>
          <X>163.5</X>
          <Y>94.625</Y>
        </Points>
        <Forces>00:00:00:00:</Forces>
      </Stroke>
      <Stroke>
        <StrokeIdx>21</StrokeIdx>
        <ID>21</ID>
        <StartDate>2004-10-28T09:14:48.0000000+01:00</StartDate>
        <StartMs>247</StartMs>
        <Duration>333</Duration>
        <Color>-14090101</Color>
        <Width>1</Width>
        <Points>
          <X>179.875</X>
          <Y>92.125</Y>
        </Points>
        <Points>
          <X>179</X>
          <Y>91.625</Y>
        </Points>
        <Points>
          <X>178.375</X>
          <Y>91.25</Y>
        </Points>
        <Points>
          <X>177.75</X>
          <Y>90.875</Y>
        </Points>
        <Points>
          <X>176.875</X>
          <Y>90.875</Y>
        </Points>
        <Points>
          <X>174.5</X>
          <Y>92.25</Y>
        </Points>
        <Points>
          <X>172.375</X>
          <Y>94.375</Y>
        </Points>
        <Points>
          <X>172.25</X>
          <Y>96.375</Y>
        </Points>
        <Points>
          <X>175.375</X>
          <Y>99.75</Y>
        </Points>
        <Points>
          <X>175.625</X>
          <Y>100.75</Y>
        </Points>
        <Points>
          <X>175.5</X>
          <Y>101.375</Y>
        </Points>
        <Points>
          <X>175</X>
          <Y>102</Y>
        </Points>
        <Points>
          <X>173.875</X>
          <Y>102.5</Y>
        </Points>
        <Points>
          <X>171.625</X>
          <Y>102.625</Y>
        </Points>
        <Points>
          <X>170.75</X>
          <Y>102.25</Y>
        </Points>
        <Points>
          <X>170.125</X>
          <Y>101.75</Y>
        </Points>
        <Points>
          <X>170.25</X>
          <Y>100.25</Y>
        </Points>
        <Forces>00:00:00:0A:08:08:06:02:04:04:04:0A:16:24:26:24:00:</Forces>
      </Stroke>
      <Stroke>
        <StrokeIdx>22</StrokeIdx>
        <ID>22</ID>
        <StartDate>2004-10-28T09:14:49.0000000+01:00</StartDate>
        <StartMs>-277</StartMs>
        <Duration>146</Duration>
        <Color>-14090101</Color>
        <Width>1</Width>
        <Points>
          <X>184.125</X>
          <Y>92.375</Y>
        </Points>
        <Points>
          <X>184</X>
          <Y>92.25</Y>
        </Points>
        <Points>
          <X>184.125</X>
          <Y>94</Y>
        </Points>
        <Points>
          <X>183.75</X>
          <Y>95.625</Y>
        </Points>
        <Points>
          <X>183.375</X>
          <Y>97</Y>
        </Points>
        <Points>
          <X>183</X>
          <Y>98</Y>
        </Points>
        <Points>
          <X>181.75</X>
          <Y>100.625</Y>
        </Points>
        <Forces>00:22:20:20:22:22:00:</Forces>
      </Stroke>
      <Stroke>
        <StrokeIdx>23</StrokeIdx>
        <ID>23</ID>
        <StartDate>2004-10-28T09:14:49.0000000+01:00</StartDate>
        <StartMs>46</StartMs>
        <Duration>266</Duration>
        <Color>-14090101</Color>
        <Width>1</Width>
        <Points>
          <X>199.625</X>
          <Y>93</Y>
        </Points>
        <Points>
          <X>199.375</X>
          <Y>92.125</Y>
        </Points>
        <Points>
          <X>199.125</X>
          <Y>91.875</Y>
        </Points>
        <Points>
          <X>199.125</X>
          <Y>91.75</Y>
        </Points>
        <Points>
          <X>198.5</X>
          <Y>91.875</Y>
        </Points>
        <Points>
          <X>197.875</X>
          <Y>92.125</Y>
        </Points>
        <Points>
          <X>196.75</X>
          <Y>92.625</Y>
        </Points>
        <Points>
          <X>194</X>
          <Y>94.625</Y>
        </Points>
        <Points>
          <X>191.75</X>
          <Y>97.5</Y>
        </Points>
        <Points>
          <X>191.375</X>
          <Y>99.25</Y>
        </Points>
        <Points>
          <X>192.5</X>
          <Y>100.5</Y>
        </Points>
        <Points>
          <X>193.375</X>
          <Y>100.75</Y>
        </Points>
        <Points>
          <X>194.625</X>
          <Y>100.75</Y>
        </Points>
        <Points>
          <X>195.5</X>
          <Y>100.5</Y>
        </Points>
        <Points>
          <X>196.125</X>
          <Y>100</Y>
        </Points>
        <Forces>00:02:14:16:1C:1E:22:24:2A:2A:2C:2E:2A:18:00:</Forces>
      </Stroke>
      <Stroke>
        <StrokeIdx>24</StrokeIdx>
        <ID>24</ID>
        <StartDate>2004-10-28T09:14:49.0000000+01:00</StartDate>
        <StartMs>447</StartMs>
        <Duration>53</Duration>
        <Color>-14090101</Color>
        <Width>1</Width>
        <Points>
          <X>195.25</X>
          <Y>88.75</Y>
        </Points>
        <Points>
          <X>194.875</X>
          <Y>87.75</Y>
        </Points>
        <Points>
          <X>195</X>
          <Y>87.75</Y>
        </Points>
        <Forces>00:20:00:</Forces>
      </Stroke>
      <Stroke>
        <StrokeIdx>25</StrokeIdx>
        <ID>25</ID>
        <StartDate>2004-10-28T09:14:53.0000000+01:00</StartDate>
        <StartMs>495</StartMs>
        <Duration>373</Duration>
        <Color>-14090101</Color>
        <Width>1</Width>
        <Points>
          <X>138.875</X>
          <Y>138.25</Y>
        </Points>
        <Points>
          <X>137.125</X>
          <Y>139.625</Y>
        </Points>
        <Points>
          <X>132.5</X>
          <Y>146.25</Y>
        </Points>
        <Points>
          <X>130.875</X>
          <Y>150.125</Y>
        </Points>
        <Points>
          <X>130.75</X>
          <Y>151.5</Y>
        </Points>
        <Points>
          <X>131.875</X>
          <Y>153.25</Y>
        </Points>
        <Points>
          <X>134.125</X>
          <Y>153.625</Y>
        </Points>
        <Points>
          <X>138</X>
          <Y>151.875</Y>
        </Points>
        <Points>
          <X>142.25</X>
          <Y>148.25</Y>
        </Points>
        <Points>
          <X>145</X>
          <Y>143</Y>
        </Points>
        <Points>
          <X>145.125</X>
          <Y>140.75</Y>
        </Points>
        <Points>
          <X>143.875</X>
          <Y>137.25</Y>
        </Points>
        <Points>
          <X>142.125</X>
          <Y>136</Y>
        </Points>
        <Points>
          <X>141.5</X>
          <Y>136.125</Y>
        </Points>
        <Points>
          <X>140.875</X>
          <Y>136.875</Y>
        </Points>
        <Forces>00:00:14:1C:1C:1A:1C:1E:24:2C:30:34:34:2A:00:</Forces>
      </Stroke>
      <Stroke>
        <StrokeIdx>26</StrokeIdx>
        <ID>26</ID>
        <StartDate>2004-10-28T09:14:54.0000000+01:00</StartDate>
        <StartMs>26</StartMs>
        <Duration>306</Duration>
        <Color>-14090101</Color>
        <Width>1</Width>
        <Points>
          <X>150</X>
          <Y>147.125</Y>
        </Points>
        <Points>
          <X>149.25</X>
          <Y>147.375</Y>
        </Points>
        <Points>
          <X>148.75</X>
          <Y>147.75</Y>
        </Points>
        <Points>
          <X>147.5</X>
          <Y>151.375</Y>
        </Points>
        <Points>
          <X>150.5</X>
          <Y>148.375</Y>
        </Points>
        <Points>
          <X>151.25</X>
          <Y>148</Y>
        </Points>
        <Points>
          <X>151.75</X>
          <Y>147.875</Y>
        </Points>
        <Points>
          <X>153.25</X>
          <Y>150</Y>
        </Points>
        <Points>
          <X>154.125</X>
          <Y>150.5</Y>
        </Points>
        <Points>
          <X>155</X>
          <Y>150.375</Y>
        </Points>
        <Forces>00:00:00:00:16:18:18:16:1A:00:</Forces>
      </Stroke>
      <Stroke>
        <StrokeIdx>27</StrokeIdx>
        <ID>27</ID>
        <StartDate>2004-10-28T09:14:55.0000000+01:00</StartDate>
        <StartMs>-331</StartMs>
        <Duration>240</Duration>
        <Color>-14090101</Color>
        <Width>1</Width>
        <Points>
          <X>170.75</X>
          <Y>135.75</Y>
        </Points>
        <Points>
          <X>170.5</X>
          <Y>135.125</Y>
        </Points>
        <Points>
          <X>168.5</X>
          <Y>141</Y>
        </Points>
        <Points>
          <X>165.5</X>
          <Y>147.625</Y>
        </Points>
        <Points>
          <X>158.75</X>
          <Y>161</Y>
        </Points>
        <Points>
          <X>158.75</X>
          <Y>160.875</Y>
        </Points>
        <Forces>00:10:24:34:40:00:</Forces>
      </Stroke>
      <Stroke>
        <StrokeIdx>28</StrokeIdx>
        <ID>28</ID>
        <StartDate>2004-10-28T09:14:55.0000000+01:00</StartDate>
        <StartMs>210</StartMs>
        <Duration>360</Duration>
        <Color>-14090101</Color>
        <Width>1</Width>
        <Points>
          <X>191.25</X>
          <Y>149.25</Y>
        </Points>
        <Points>
          <X>191.25</X>
          <Y>148.75</Y>
        </Points>
        <Points>
          <X>189.25</X>
          <Y>149.75</Y>
        </Points>
        <Points>
          <X>187.625</X>
          <Y>151.125</Y>
        </Points>
        <Points>
          <X>187.125</X>
          <Y>151.875</Y>
        </Points>
        <Points>
          <X>187.125</X>
          <Y>153.625</Y>
        </Points>
        <Points>
          <X>187.75</X>
          <Y>154.25</Y>
        </Points>
        <Points>
          <X>188.5</X>
          <Y>154.625</Y>
        </Points>
        <Points>
          <X>190.25</X>
          <Y>153.875</Y>
        </Points>
        <Points>
          <X>193.375</X>
          <Y>148.625</Y>
        </Points>
        <Points>
          <X>195.625</X>
          <Y>146.625</Y>
        </Points>
        <Points>
          <X>196.5</X>
          <Y>146.375</Y>
        </Points>
        <Points>
          <X>196.875</X>
          <Y>146.875</Y>
        </Points>
        <Points>
          <X>197.25</X>
          <Y>147.5</Y>
        </Points>
        <Points>
          <X>199.25</X>
          <Y>148.5</Y>
        </Points>
        <Forces>00:00:14:16:16:18:16:14:14:16:14:12:06:00:00:</Forces>
      </Stroke>
      <Stroke>
        <StrokeIdx>29</StrokeIdx>
        <ID>29</ID>
        <StartDate>2004-10-28T09:14:56.0000000+01:00</StartDate>
        <StartMs>-289</StartMs>
        <Duration>293</Duration>
        <Color>-14090101</Color>
        <Width>1</Width>
        <Points>
          <X>206.875</X>
          <Y>138.125</Y>
        </Points>
        <Points>
          <X>206.5</X>
          <Y>138</Y>
        </Points>
        <Points>
          <X>205.75</X>
          <Y>142.375</Y>
        </Points>
        <Points>
          <X>203.625</X>
          <Y>149.625</Y>
        </Points>
        <Points>
          <X>198.5</X>
          <Y>162.625</Y>
        </Points>
        <Points>
          <X>196.25</X>
          <Y>170.125</Y>
        </Points>
        <Points>
          <X>196.25</X>
          <Y>172.375</Y>
        </Points>
        <Points>
          <X>196.75</X>
          <Y>173.375</Y>
        </Points>
        <Points>
          <X>199.5</X>
          <Y>169.25</Y>
        </Points>
        <Points>
          <X>203.75</X>
          <Y>157.625</Y>
        </Points>
        <Forces>00:06:14:26:32:32:2E:22:2A:00:</Forces>
      </Stroke>
      <Stroke>
        <StrokeIdx>30</StrokeIdx>
        <ID>30</ID>
        <StartDate>2004-10-28T09:14:56.0000000+01:00</StartDate>
        <StartMs>127</StartMs>
        <Duration>320</Duration>
        <Color>-14090101</Color>
        <Width>1</Width>
        <Points>
          <X>218.125</X>
          <Y>139</Y>
        </Points>
        <Points>
          <X>217.625</X>
          <Y>138.875</Y>
        </Points>
        <Points>
          <X>217</X>
          <Y>140</Y>
        </Points>
        <Points>
          <X>215.125</X>
          <Y>147.625</Y>
        </Points>
        <Points>
          <X>213.75</X>
          <Y>151.375</Y>
        </Points>
        <Points>
          <X>208.375</X>
          <Y>167.375</Y>
        </Points>
        <Points>
          <X>208.375</X>
          <Y>168.625</Y>
        </Points>
        <Points>
          <X>208.625</X>
          <Y>169</Y>
        </Points>
        <Points>
          <X>209.125</X>
          <Y>169.125</Y>
        </Points>
        <Points>
          <X>209.875</X>
          <Y>168.875</Y>
        </Points>
        <Points>
          <X>212.5</X>
          <Y>166</Y>
        </Points>
        <Points>
          <X>213.625</X>
          <Y>163.5</Y>
        </Points>
        <Points>
          <X>214.375</X>
          <Y>160.5</Y>
        </Points>
        <Points>
          <X>214.25</X>
          <Y>158.375</Y>
        </Points>
        <Points>
          <X>213.625</X>
          <Y>157.125</Y>
        </Points>
        <Points>
          <X>213</X>
          <Y>156.25</Y>
        </Points>
        <Points>
          <X>212.125</X>
          <Y>156</Y>
        </Points>
        <Forces>00:00:16:32:3A:3E:3C:36:36:36:3E:40:40:40:40:2C:00:</Forces>
      </Stroke>
      <Stroke>
        <StrokeIdx>31</StrokeIdx>
        <ID>31</ID>
        <StartDate>2004-10-28T09:14:57.0000000+01:00</StartDate>
        <StartMs>-81</StartMs>
        <Duration>333</Duration>
        <Color>-14090101</Color>
        <Width>1</Width>
        <Points>
          <X>250.5</X>
          <Y>136.25</Y>
        </Points>
        <Points>
          <X>250</X>
          <Y>134.5</Y>
        </Points>
        <Points>
          <X>249.875</X>
          <Y>134.5</Y>
        </Points>
        <Points>
          <X>246.25</X>
          <Y>147.625</Y>
        </Points>
        <Points>
          <X>244.75</X>
          <Y>150.375</Y>
        </Points>
        <Points>
          <X>245.25</X>
          <Y>149.625</Y>
        </Points>
        <Points>
          <X>246.625</X>
          <Y>148.25</Y>
        </Points>
        <Points>
          <X>248.125</X>
          <Y>147.625</Y>
        </Points>
        <Points>
          <X>249.5</X>
          <Y>147.75</Y>
        </Points>
        <Points>
          <X>250.75</X>
          <Y>148.5</Y>
        </Points>
        <Points>
          <X>251.625</X>
          <Y>149.5</Y>
        </Points>
        <Points>
          <X>251.625</X>
          <Y>150.875</Y>
        </Points>
        <Points>
          <X>251.25</X>
          <Y>152</Y>
        </Points>
        <Points>
          <X>248.875</X>
          <Y>153.875</Y>
        </Points>
        <Points>
          <X>245.75</X>
          <Y>154.375</Y>
        </Points>
        <Forces>00:00:08:1A:2C:32:24:20:1E:1A:18:1A:1A:22:00:</Forces>
      </Stroke>
      <Stroke>
        <StrokeIdx>32</StrokeIdx>
        <ID>32</ID>
        <StartDate>2004-10-28T09:14:57.0000000+01:00</StartDate>
        <StartMs>371</StartMs>
        <Duration>133</Duration>
        <Color>-14090101</Color>
        <Width>1</Width>
        <Points>
          <X>256.375</X>
          <Y>149.125</Y>
        </Points>
        <Points>
          <X>255.625</X>
          <Y>151.125</Y>
        </Points>
        <Points>
          <X>255.75</X>
          <Y>152.25</Y>
        </Points>
        <Points>
          <X>256.375</X>
          <Y>153.25</Y>
        </Points>
        <Points>
          <X>257.25</X>
          <Y>153.875</Y>
        </Points>
        <Points>
          <X>259.625</X>
          <Y>153.75</Y>
        </Points>
        <Points>
          <X>260.5</X>
          <Y>153.125</Y>
        </Points>
        <Points>
          <X>261.125</X>
          <Y>152.125</Y>
        </Points>
        <Forces>00:00:08:08:14:28:28:14:</Forces>
      </Stroke>
      <Stroke>
        <StrokeIdx>33</StrokeIdx>
        <ID>33</ID>
        <StartDate>2004-10-28T09:14:58.0000000+01:00</StartDate>
        <StartMs>-373</StartMs>
        <Duration>106</Duration>
        <Color>-14090101</Color>
        <Width>1</Width>
        <Points>
          <X>273.375</X>
          <Y>138.625</Y>
        </Points>
        <Points>
          <X>272.875</X>
          <Y>138.375</Y>
        </Points>
        <Points>
          <X>272.625</X>
          <Y>138.75</Y>
        </Points>
        <Points>
          <X>272.25</X>
          <Y>139.75</Y>
        </Points>
        <Points>
          <X>270.125</X>
          <Y>147.25</Y>
        </Points>
        <Points>
          <X>269.25</X>
          <Y>150.125</Y>
        </Points>
        <Points>
          <X>268.25</X>
          <Y>152.75</Y>
        </Points>
        <Forces>00:00:1A:1E:2C:2A:00:</Forces>
      </Stroke>
      <Stroke>
        <StrokeIdx>34</StrokeIdx>
        <ID>34</ID>
        <StartDate>2004-10-28T09:14:58.0000000+01:00</StartDate>
        <StartMs>-149</StartMs>
        <Duration>93</Duration>
        <Color>-14090101</Color>
        <Width>1</Width>
        <Points>
          <X>279.25</X>
          <Y>141</Y>
        </Points>
        <Points>
          <X>278.5</X>
          <Y>141</Y>
        </Points>
        <Points>
          <X>277.75</X>
          <Y>144.75</Y>
        </Points>
        <Points>
          <X>276.375</X>
          <Y>149.5</Y>
        </Points>
        <Forces>00:28:28:00:</Forces>
      </Stroke>
      <Stroke>
        <StrokeIdx>35</StrokeIdx>
        <ID>35</ID>
        <StartDate>2004-10-28T09:14:58.0000000+01:00</StartDate>
        <StartMs>35</StartMs>
        <Duration>333</Duration>
        <Color>-14090101</Color>
        <Width>1</Width>
        <Points>
          <X>269.125</X>
          <Y>148</Y>
        </Points>
        <Points>
          <X>269.25</X>
          <Y>146.625</Y>
        </Points>
        <Points>
          <X>269.75</X>
          <Y>146</Y>
        </Points>
        <Points>
          <X>273.5</X>
          <Y>145</Y>
        </Points>
        <Points>
          <X>279.875</X>
          <Y>144.625</Y>
        </Points>
        <Points>
          <X>286.25</X>
          <Y>145.5</Y>
        </Points>
        <Points>
          <X>286.625</X>
          <Y>146</Y>
        </Points>
        <Points>
          <X>286.5</X>
          <Y>146.625</Y>
        </Points>
        <Points>
          <X>283</X>
          <Y>151.125</Y>
        </Points>
        <Points>
          <X>283.125</X>
          <Y>152.25</Y>
        </Points>
        <Points>
          <X>283.5</X>
          <Y>153</Y>
        </Points>
        <Points>
          <X>284.375</X>
          <Y>153.125</Y>
        </Points>
        <Points>
          <X>287.25</X>
          <Y>152</Y>
        </Points>
        <Points>
          <X>288.25</X>
          <Y>150.875</Y>
        </Points>
        <Points>
          <X>288.875</X>
          <Y>147.875</Y>
        </Points>
        <Points>
          <X>288.5</X>
          <Y>146.125</Y>
        </Points>
        <Points>
          <X>288</X>
          <Y>145.25</Y>
        </Points>
        <Forces>00:00:00:00:00:00:00:00:1E:1C:14:14:22:28:34:26:00:</Forces>
      </Stroke>
      <Stroke>
        <StrokeIdx>36</StrokeIdx>
        <ID>36</ID>
        <StartDate>2004-10-28T09:14:58.0000000+01:00</StartDate>
        <StartMs>487</StartMs>
        <Duration>253</Duration>
        <Color>-14090101</Color>
        <Width>1</Width>
        <Points>
          <X>295.75</X>
          <Y>148.25</Y>
        </Points>
        <Points>
          <X>294.25</X>
          <Y>150.625</Y>
        </Points>
        <Points>
          <X>294</X>
          <Y>152.375</Y>
        </Points>
        <Points>
          <X>295.875</X>
          <Y>149.125</Y>
        </Points>
        <Points>
          <X>299.625</X>
          <Y>146.75</Y>
        </Points>
        <Points>
          <X>300.5</X>
          <Y>146.75</Y>
        </Points>
        <Points>
          <X>300.75</X>
          <Y>147</Y>
        </Points>
        <Points>
          <X>301.125</X>
          <Y>149</Y>
        </Points>
        <Points>
          <X>300.625</X>
          <Y>150.875</Y>
        </Points>
        <Points>
          <X>299.75</X>
          <Y>152.625</Y>
        </Points>
        <Forces>00:26:34:46:46:46:44:42:32:00:</Forces>
      </Stroke>
      <Stroke>
        <StrokeIdx>37</StrokeIdx>
        <ID>37</ID>
        <StartDate>2004-10-28T09:15:16.0000000+01:00</StartDate>
        <StartMs>-199</StartMs>
        <Duration>240</Duration>
        <Color>-14090101</Color>
        <Width>1</Width>
        <Points>
          <X>138.125</X>
          <Y>190.375</Y>
        </Points>
        <Points>
          <X>140.25</X>
          <Y>192.25</Y>
        </Points>
        <Points>
          <X>141.5</X>
          <Y>194.5</Y>
        </Points>
        <Points>
          <X>144.125</X>
          <Y>202</Y>
        </Points>
        <Points>
          <X>145.75</X>
          <Y>205</Y>
        </Points>
        <Points>
          <X>146.125</X>
          <Y>204.875</Y>
        </Points>
        <Points>
          <X>147</X>
          <Y>204.25</Y>
        </Points>
        <Points>
          <X>150.125</X>
          <Y>200</Y>
        </Points>
        <Points>
          <X>153.25</X>
          <Y>194.125</Y>
        </Points>
        <Points>
          <X>154.875</X>
          <Y>190.75</Y>
        </Points>
        <Forces>00:00:00:02:0A:1C:32:42:48:00:</Forces>
      </Stroke>
      <Stroke>
        <StrokeIdx>38</StrokeIdx>
        <ID>38</ID>
        <StartDate>2004-10-28T09:15:16.0000000+01:00</StartDate>
        <StartMs>147</StartMs>
        <Duration>213</Duration>
        <Color>-14090101</Color>
        <Width>1</Width>
        <Points>
          <X>158.5</X>
          <Y>193.125</Y>
        </Points>
        <Points>
          <X>156.5</X>
          <Y>195.5</Y>
        </Points>
        <Points>
          <X>155.25</X>
          <Y>198.75</Y>
        </Points>
        <Points>
          <X>155.375</X>
          <Y>200.625</Y>
        </Points>
        <Points>
          <X>156</X>
          <Y>202.125</Y>
        </Points>
        <Points>
          <X>157</X>
          <Y>203</Y>
        </Points>
        <Points>
          <X>158.125</X>
          <Y>202.875</Y>
        </Points>
        <Points>
          <X>161.125</X>
          <Y>200.25</Y>
        </Points>
        <Points>
          <X>162.125</X>
          <Y>198.25</Y>
        </Points>
        <Points>
          <X>162.625</X>
          <Y>196</Y>
        </Points>
        <Points>
          <X>162.75</X>
          <Y>194.25</Y>
        </Points>
        <Points>
          <X>162.25</X>
          <Y>193.25</Y>
        </Points>
        <Points>
          <X>161.625</X>
          <Y>192.625</Y>
        </Points>
        <Points>
          <X>161</X>
          <Y>192.5</Y>
        </Points>
        <Forces>00:00:14:14:12:12:0E:20:20:24:22:16:00:00:</Forces>
      </Stroke>
      <Stroke>
        <StrokeIdx>39</StrokeIdx>
        <ID>39</ID>
        <StartDate>2004-10-28T09:15:17.0000000+01:00</StartDate>
        <StartMs>-292</StartMs>
        <Duration>240</Duration>
        <Color>-14090101</Color>
        <Width>1</Width>
        <Points>
          <X>182.75</X>
          <Y>176</Y>
        </Points>
        <Points>
          <X>182.125</X>
          <Y>176.625</Y>
        </Points>
        <Points>
          <X>177.75</X>
          <Y>188.5</Y>
        </Points>
        <Points>
          <X>175.75</X>
          <Y>193</Y>
        </Points>
        <Points>
          <X>170.875</X>
          <Y>203.625</Y>
        </Points>
        <Points>
          <X>170.875</X>
          <Y>203.625</Y>
        </Points>
        <Points>
          <X>170.75</X>
          <Y>203.5</Y>
        </Points>
        <Forces>00:24:3C:42:52:3A:08:</Forces>
      </Stroke>
      <Stroke>
        <StrokeIdx>40</StrokeIdx>
        <ID>40</ID>
        <StartDate>2004-10-28T09:15:17.0000000+01:00</StartDate>
        <StartMs>214</StartMs>
        <Duration>226</Duration>
        <Color>-14090101</Color>
        <Width>1</Width>
        <Points>
          <X>196.5</X>
          <Y>197.5</Y>
        </Points>
        <Points>
          <X>195.5</X>
          <Y>196.5</Y>
        </Points>
        <Points>
          <X>200.375</X>
          <Y>196.875</Y>
        </Points>
        <Points>
          <X>207.875</X>
          <Y>195.375</Y>
        </Points>
        <Points>
          <X>207.125</X>
          <Y>195.375</Y>
        </Points>
        <Forces>00:16:30:48:00:</Forces>
      </Stroke>
      <Stroke>
        <StrokeIdx>41</StrokeIdx>
        <ID>41</ID>
        <StartDate>2004-10-28T09:15:18.0000000+01:00</StartDate>
        <StartMs>-158</StartMs>
        <Duration>173</Duration>
        <Color>-14090101</Color>
        <Width>1</Width>
        <Points>
          <X>267.25</X>
          <Y>184</Y>
        </Points>
        <Points>
          <X>267.125</X>
          <Y>183.125</Y>
        </Points>
        <Points>
          <X>267</X>
          <Y>182.625</Y>
        </Points>
        <Points>
          <X>266.875</X>
          <Y>182.625</Y>
        </Points>
        <Points>
          <X>261.375</X>
          <Y>194.25</Y>
        </Points>
        <Points>
          <X>259.625</X>
          <Y>199.5</Y>
        </Points>
        <Points>
          <X>258.75</X>
          <Y>201.5</Y>
        </Points>
        <Points>
          <X>257.25</X>
          <Y>203.5</Y>
        </Points>
        <Forces>00:00:0A:26:40:40:38:00:</Forces>
      </Stroke>
      <Stroke>
        <StrokeIdx>42</StrokeIdx>
        <ID>42</ID>
        <StartDate>2004-10-28T09:15:18.0000000+01:00</StartDate>
        <StartMs>131</StartMs>
        <Duration>133</Duration>
        <Color>-14090101</Color>
        <Width>1</Width>
        <Points>
          <X>254.75</X>
          <Y>194.375</Y>
        </Points>
        <Points>
          <X>254.875</X>
          <Y>193.875</Y>
        </Points>
        <Points>
          <X>263.875</X>
          <Y>192</Y>
        </Points>
        <Points>
          <X>265.875</X>
          <Y>191.875</Y>
        </Points>
        <Points>
          <X>270.75</X>
          <Y>192</Y>
        </Points>
        <Forces>00:1C:2C:2C:00:</Forces>
      </Stroke>
      <Stroke>
        <StrokeIdx>43</StrokeIdx>
        <ID>43</ID>
        <StartDate>2004-10-28T09:15:18.0000000+01:00</StartDate>
        <StartMs>421</StartMs>
        <Duration>240</Duration>
        <Color>-14090101</Color>
        <Width>1</Width>
        <Points>
          <X>300.5</X>
          <Y>195.25</Y>
        </Points>
        <Points>
          <X>299.75</X>
          <Y>194.375</Y>
        </Points>
        <Points>
          <X>299.875</X>
          <Y>194.375</Y>
        </Points>
        <Points>
          <X>302.375</X>
          <Y>194.875</Y>
        </Points>
        <Points>
          <X>306.25</X>
          <Y>194.875</Y>
        </Points>
        <Points>
          <X>311.25</X>
          <Y>194.375</Y>
        </Points>
        <Points>
          <X>311.125</X>
          <Y>194.25</Y>
        </Points>
        <Points>
          <X>310.875</X>
          <Y>194.25</Y>
        </Points>
        <Forces>1A:34:50:54:5C:64:5A:00:</Forces>
      </Stroke>
      <Stroke>
        <StrokeIdx>44</StrokeIdx>
        <ID>44</ID>
        <StartDate>2004-10-28T09:15:19.0000000+01:00</StartDate>
        <StartMs>157</StartMs>
        <Duration>186</Duration>
        <Color>-14090101</Color>
        <Width>1</Width>
        <Points>
          <X>361</X>
          <Y>205</Y>
        </Points>
        <Points>
          <X>361.5</X>
          <Y>204.875</Y>
        </Points>
        <Points>
          <X>361.5</X>
          <Y>205.375</Y>
        </Points>
        <Points>
          <X>361.5</X>
          <Y>206</Y>
        </Points>
        <Points>
          <X>361.5</X>
          <Y>207.125</Y>
        </Points>
        <Points>
          <X>361.125</X>
          <Y>208.625</Y>
        </Points>
        <Points>
          <X>360.75</X>
          <Y>210</Y>
        </Points>
        <Points>
          <X>360.25</X>
          <Y>211.375</Y>
        </Points>
        <Points>
          <X>359.25</X>
          <Y>213.125</Y>
        </Points>
        <Points>
          <X>357.5</X>
          <Y>215.25</Y>
        </Points>
        <Points>
          <X>356.5</X>
          <Y>216.625</Y>
        </Points>
        <Forces>00:2C:3E:46:4C:50:50:54:54:40:00:</Forces>
      </Stroke>
      <Stroke>
        <StrokeIdx>45</StrokeIdx>
        <ID>45</ID>
        <StartDate>2004-10-28T09:15:21.0000000+01:00</StartDate>
        <StartMs>-280</StartMs>
        <Duration>200</Duration>
        <Color>-14090101</Color>
        <Width>1</Width>
        <Points>
          <X>412.5</X>
          <Y>188.25</Y>
        </Points>
        <Points>
          <X>412</X>
          <Y>189.5</Y>
        </Points>
        <Points>
          <X>409</X>
          <Y>197.625</Y>
        </Points>
        <Points>
          <X>407.25</X>
          <Y>203.75</Y>
        </Points>
        <Points>
          <X>407</X>
          <Y>204.5</Y>
        </Points>
        <Forces>00:00:22:30:00:</Forces>
      </Stroke>
      <Stroke>
        <StrokeIdx>46</StrokeIdx>
        <ID>46</ID>
        <StartDate>2004-10-28T09:15:21.0000000+01:00</StartDate>
        <StartMs>156</StartMs>
        <Duration>1360</Duration>
        <Color>-14090101</Color>
        <Width>1</Width>
        <Points>
          <X>419.5</X>
          <Y>187.875</Y>
        </Points>
        <Points>
          <X>418</X>
          <Y>188.125</Y>
        </Points>
        <Points>
          <X>416.375</X>
          <Y>189.375</Y>
        </Points>
        <Points>
          <X>411.75</X>
          <Y>194.125</Y>
        </Points>
        <Points>
          <X>409.75</X>
          <Y>196.875</Y>
        </Points>
        <Points>
          <X>407.75</X>
          <Y>201.875</Y>
        </Points>
        <Points>
          <X>408.25</X>
          <Y>204.375</Y>
        </Points>
        <Points>
          <X>408.875</X>
          <Y>205</Y>
        </Points>
        <Points>
          <X>410</X>
          <Y>205.375</Y>
        </Points>
        <Points>
          <X>412.375</X>
          <Y>204.875</Y>
        </Points>
        <Points>
          <X>415.75</X>
          <Y>203.25</Y>
        </Points>
        <Points>
          <X>419.625</X>
          <Y>200.25</Y>
        </Points>
        <Points>
          <X>427.125</X>
          <Y>192.125</Y>
        </Points>
        <Points>
          <X>429</X>
          <Y>189.375</Y>
        </Points>
        <Points>
          <X>429.375</X>
          <Y>188.25</Y>
        </Points>
        <Points>
          <X>429.375</X>
          <Y>187.875</Y>
        </Points>
        <Points>
          <X>427.375</X>
          <Y>194.125</Y>
        </Points>
        <Points>
          <X>422.75</X>
          <Y>204</Y>
        </Points>
        <Points>
          <X>426</X>
          <Y>201.75</Y>
        </Points>
        <Points>
          <X>429.375</X>
          <Y>200.625</Y>
        </Points>
        <Points>
          <X>430.5</X>
          <Y>204.5</Y>
        </Points>
        <Points>
          <X>431.125</X>
          <Y>205</Y>
        </Points>
        <Points>
          <X>432</X>
          <Y>205.125</Y>
        </Points>
        <Points>
          <X>433.25</X>
          <Y>205.125</Y>
        </Points>
        <Points>
          <X>436.375</X>
          <Y>203.875</Y>
        </Points>
        <Points>
          <X>437.625</X>
          <Y>202.875</Y>
        </Points>
        <Points>
          <X>438.25</X>
          <Y>202</Y>
        </Points>
        <Points>
          <X>438.25</X>
          <Y>201.25</Y>
        </Points>
        <Points>
          <X>437.875</X>
          <Y>200.5</Y>
        </Points>
        <Points>
          <X>437.5</X>
          <Y>200</Y>
        </Points>
        <Points>
          <X>437.375</X>
          <Y>200</Y>
        </Points>
        <Points>
          <X>435</X>
          <Y>204.625</Y>
        </Points>
        <Points>
          <X>435</X>
          <Y>206.125</Y>
        </Points>
        <Points>
          <X>436.75</X>
          <Y>206.125</Y>
        </Points>
        <Points>
          <X>438.375</X>
          <Y>205.5</Y>
        </Points>
        <Points>
          <X>444</X>
          <Y>201.875</Y>
        </Points>
        <Points>
          <X>444.625</X>
          <Y>201.25</Y>
        </Points>
        <Points>
          <X>443.375</X>
          <Y>204</Y>
        </Points>
        <Points>
          <X>443.375</X>
          <Y>204.75</Y>
        </Points>
        <Points>
          <X>443.5</X>
          <Y>205.25</Y>
        </Points>
        <Points>
          <X>444.125</X>
          <Y>205.5</Y>
        </Points>
        <Points>
          <X>444.875</X>
          <Y>205.25</Y>
        </Points>
        <Points>
          <X>445.75</X>
          <Y>204.625</Y>
        </Points>
        <Points>
          <X>449.875</X>
          <Y>200.25</Y>
        </Points>
        <Points>
          <X>452.125</X>
          <Y>199.25</Y>
        </Points>
        <Points>
          <X>452.5</X>
          <Y>199.25</Y>
        </Points>
        <Points>
          <X>453</X>
          <Y>201.875</Y>
        </Points>
        <Points>
          <X>452.25</X>
          <Y>205.125</Y>
        </Points>
        <Points>
          <X>452.25</X>
          <Y>205.125</Y>
        </Points>
        <Points>
          <X>452.25</X>
          <Y>205.125</Y>
        </Points>
        <Points>
          <X>454.125</X>
          <Y>203.375</Y>
        </Points>
        <Points>
          <X>456.875</X>
          <Y>201.5</Y>
        </Points>
        <Points>
          <X>458.625</X>
          <Y>200.875</Y>
        </Points>
        <Points>
          <X>458.625</X>
          <Y>200.75</Y>
        </Points>
        <Points>
          <X>458.5</X>
          <Y>201.25</Y>
        </Points>
        <Forces>00:14:1E:30:34:3A:3A:32:22:16:00:00:00:00:00:36:36:3E:3E:3C:32:2C:2C:2E:30:30:32:34:36:38:3A:32:28:1E:20:1C:1E:28:28:28:22:26:28:2C:2C:2C:2C:2E:2E:30:3E:3C:3A:2A:00:</Forces>
      </Stroke>
      <Stroke>
        <StrokeIdx>47</StrokeIdx>
        <ID>47</ID>
        <StartDate>2004-10-28T09:15:23.0000000+01:00</StartDate>
        <StartMs>-114</StartMs>
        <Duration>120</Duration>
        <Color>-14090101</Color>
        <Width>1</Width>
        <Points>
          <X>442.75</X>
          <Y>198.75</Y>
        </Points>
        <Points>
          <X>443.125</X>
          <Y>202.125</Y>
        </Points>
        <Points>
          <X>443.25</X>
          <Y>203.625</Y>
        </Points>
        <Points>
          <X>444.25</X>
          <Y>206.5</Y>
        </Points>
        <Forces>00:1C:26:00:</Forces>
      </Stroke>
      <Stroke>
        <StrokeIdx>48</StrokeIdx>
        <ID>48</ID>
        <StartDate>2004-10-28T09:15:23.0000000+01:00</StartDate>
        <StartMs>363</StartMs>
        <Duration>133</Duration>
        <Color>-14090101</Color>
        <Width>1</Width>
        <Points>
          <X>445</X>
          <Y>197.75</Y>
        </Points>
        <Points>
          <X>444.375</X>
          <Y>196.875</Y>
        </Points>
        <Points>
          <X>443.75</X>
          <Y>197</Y>
        </Points>
        <Points>
          <X>440.5</X>
          <Y>198.875</Y>
        </Points>
        <Points>
          <X>438.875</X>
          <Y>200.5</Y>
        </Points>
        <Points>
          <X>436.75</X>
          <Y>203.25</Y>
        </Points>
        <Points>
          <X>436.625</X>
          <Y>204.5</Y>
        </Points>
        <Points>
          <X>437.375</X>
          <Y>205.5</Y>
        </Points>
        <Forces>00:00:00:0A:1A:1E:0C:00:</Forces>
      </Stroke>
      <Stroke>
        <StrokeIdx>49</StrokeIdx>
        <ID>49</ID>
        <StartDate>2004-10-28T09:15:24.0000000+01:00</StartDate>
        <StartMs>-239</StartMs>
        <Duration>226</Duration>
        <Color>-14090101</Color>
        <Width>1</Width>
        <Points>
          <X>462.75</X>
          <Y>200.125</Y>
        </Points>
        <Points>
          <X>461.375</X>
          <Y>204.25</Y>
        </Points>
        <Points>
          <X>461.25</X>
          <Y>204</Y>
        </Points>
        <Forces>00:24:00:</Forces>
      </Stroke>
      <Stroke>
        <StrokeIdx>50</StrokeIdx>
        <ID>50</ID>
        <StartDate>2004-10-28T09:15:24.0000000+01:00</StartDate>
        <StartMs>125</StartMs>
        <Duration>133</Duration>
        <Color>-14090101</Color>
        <Width>1</Width>
        <Points>
          <X>458.625</X>
          <Y>199.625</Y>
        </Points>
        <Points>
          <X>459.5</X>
          <Y>200.375</Y>
        </Points>
        <Points>
          <X>460.25</X>
          <Y>203.375</Y>
        </Points>
        <Points>
          <X>459.625</X>
          <Y>207</Y>
        </Points>
        <Points>
          <X>459.25</X>
          <Y>207.75</Y>
        </Points>
        <Points>
          <X>458.875</X>
          <Y>208.375</Y>
        </Points>
        <Forces>00:00:16:14:00:00:</Forces>
      </Stroke>
      <Stroke>
        <StrokeIdx>51</StrokeIdx>
        <ID>51</ID>
        <StartDate>2004-10-28T09:15:24.0000000+01:00</StartDate>
        <StartMs>426</StartMs>
        <Duration>1026</Duration>
        <Color>-14090101</Color>
        <Width>1</Width>
        <Points>
          <X>463.25</X>
          <Y>202.375</Y>
        </Points>
        <Points>
          <X>462.375</X>
          <Y>202.125</Y>
        </Points>
        <Points>
          <X>462.125</X>
          <Y>201.875</Y>
        </Points>
        <Points>
          <X>465</X>
          <Y>201.375</Y>
        </Points>
        <Points>
          <X>464</X>
          <Y>204.75</Y>
        </Points>
        <Points>
          <X>463.625</X>
          <Y>205.625</Y>
        </Points>
        <Points>
          <X>463.375</X>
          <Y>206</Y>
        </Points>
        <Points>
          <X>463.25</X>
          <Y>206</Y>
        </Points>
        <Points>
          <X>463.375</X>
          <Y>205.875</Y>
        </Points>
        <Points>
          <X>466.5</X>
          <Y>202.625</Y>
        </Points>
        <Points>
          <X>469.25</X>
          <Y>201.375</Y>
        </Points>
        <Points>
          <X>469.625</X>
          <Y>201.625</Y>
        </Points>
        <Points>
          <X>470.25</X>
          <Y>205</Y>
        </Points>
        <Points>
          <X>471.25</X>
          <Y>206</Y>
        </Points>
        <Points>
          <X>473.375</X>
          <Y>205.75</Y>
        </Points>
        <Points>
          <X>475</X>
          <Y>205.25</Y>
        </Points>
        <Points>
          <X>476.75</X>
          <Y>204</Y>
        </Points>
        <Points>
          <X>477.375</X>
          <Y>202</Y>
        </Points>
        <Points>
          <X>477.125</X>
          <Y>201.5</Y>
        </Points>
        <Points>
          <X>476.75</X>
          <Y>201.25</Y>
        </Points>
        <Points>
          <X>476.125</X>
          <Y>201.125</Y>
        </Points>
        <Points>
          <X>474.5</X>
          <Y>203.125</Y>
        </Points>
        <Points>
          <X>474.25</X>
          <Y>205.125</Y>
        </Points>
        <Points>
          <X>474.875</X>
          <Y>206</Y>
        </Points>
        <Points>
          <X>477.125</X>
          <Y>206</Y>
        </Points>
        <Points>
          <X>480.875</X>
          <Y>204.625</Y>
        </Points>
        <Points>
          <X>484.625</X>
          <Y>201.375</Y>
        </Points>
        <Points>
          <X>491.625</X>
          <Y>191.875</Y>
        </Points>
        <Points>
          <X>493.625</X>
          <Y>187.25</Y>
        </Points>
        <Points>
          <X>493.5</X>
          <Y>185.5</Y>
        </Points>
        <Points>
          <X>493.125</X>
          <Y>185.375</Y>
        </Points>
        <Points>
          <X>492</X>
          <Y>186.375</Y>
        </Points>
        <Points>
          <X>489.375</X>
          <Y>190.75</Y>
        </Points>
        <Points>
          <X>484.5</X>
          <Y>202</Y>
        </Points>
        <Points>
          <X>484.5</X>
          <Y>205.875</Y>
        </Points>
        <Points>
          <X>485</X>
          <Y>206.25</Y>
        </Points>
        <Points>
          <X>485.75</X>
          <Y>206.625</Y>
        </Points>
        <Points>
          <X>486.75</X>
          <Y>206.5</Y>
        </Points>
        <Points>
          <X>488.25</X>
          <Y>206</Y>
        </Points>
        <Forces>00:00:00:16:20:22:22:24:24:1C:18:12:0E:04:02:04:08:10:1A:1A:1C:1A:1A:1A:1E:22:26:24:28:34:36:32:32:36:38:38:34:26:00:</Forces>
      </Stroke>
      <Stroke>
        <StrokeIdx>52</StrokeIdx>
        <ID>52</ID>
        <StartDate>2004-10-28T09:15:26.0000000+01:00</StartDate>
        <StartMs>-390</StartMs>
        <Duration>120</Duration>
        <Color>-14090101</Color>
        <Width>1</Width>
        <Points>
          <X>494.5</X>
          <Y>200.75</Y>
        </Points>
        <Points>
          <X>494.625</X>
          <Y>200.625</Y>
        </Points>
        <Points>
          <X>499.75</X>
          <Y>201</Y>
        </Points>
        <Points>
          <X>499.875</X>
          <Y>200.75</Y>
        </Points>
        <Forces>00:2C:2E:00:</Forces>
      </Stroke>
      <Stroke>
        <StrokeIdx>53</StrokeIdx>
        <ID>53</ID>
        <StartDate>2004-10-28T09:15:26.0000000+01:00</StartDate>
        <StartMs>441</StartMs>
        <Duration>200</Duration>
        <Color>-14090101</Color>
        <Width>1</Width>
        <Points>
          <X>540.875</X>
          <Y>195.25</Y>
        </Points>
        <Points>
          <X>540.75</X>
          <Y>194.75</Y>
        </Points>
        <Points>
          <X>539.125</X>
          <Y>199.375</Y>
        </Points>
        <Points>
          <X>534.125</X>
          <Y>210.5</Y>
        </Points>
        <Points>
          <X>533.625</X>
          <Y>211.375</Y>
        </Points>
        <Forces>00:0A:1E:38:00:</Forces>
      </Stroke>
      <Stroke>
        <StrokeIdx>54</StrokeIdx>
        <ID>54</ID>
        <StartDate>2004-10-28T09:15:27.0000000+01:00</StartDate>
        <StartMs>-213</StartMs>
        <Duration>240</Duration>
        <Color>-14090101</Color>
        <Width>1</Width>
        <Points>
          <X>530.75</X>
          <Y>203.375</Y>
        </Points>
        <Points>
          <X>530.5</X>
          <Y>202.75</Y>
        </Points>
        <Points>
          <X>537.25</X>
          <Y>203.125</Y>
        </Points>
        <Points>
          <X>544</X>
          <Y>202.375</Y>
        </Points>
        <Points>
          <X>543.875</X>
          <Y>202.25</Y>
        </Points>
        <Points>
          <X>543.75</X>
          <Y>202.25</Y>
        </Points>
        <Forces>00:12:48:58:46:06:</Forces>
      </Stroke>
      <Stroke>
        <StrokeIdx>55</StrokeIdx>
        <ID>55</ID>
        <StartDate>2004-10-28T09:15:27.0000000+01:00</StartDate>
        <StartMs>497</StartMs>
        <Duration>440</Duration>
        <Color>-14090101</Color>
        <Width>1</Width>
        <Points>
          <X>560.875</X>
          <Y>202.125</Y>
        </Points>
        <Points>
          <X>560.75</X>
          <Y>202.25</Y>
        </Points>
        <Points>
          <X>561.25</X>
          <Y>202.25</Y>
        </Points>
        <Points>
          <X>571</X>
          <Y>201.625</Y>
        </Points>
        <Points>
          <X>570.875</X>
          <Y>201.5</Y>
        </Points>
        <Points>
          <X>570.625</X>
          <Y>201.375</Y>
        </Points>
        <Forces>00:54:6A:6C:60:10:</Forces>
      </Stroke>
      <Stroke>
        <StrokeIdx>56</StrokeIdx>
        <ID>56</ID>
        <StartDate>2004-10-28T09:16:29.0000000+01:00</StartDate>
        <StartMs>-360</StartMs>
        <Duration>453</Duration>
        <Color>-14090101</Color>
        <Width>1</Width>
        <Points>
          <X>148.75</X>
          <Y>220.5</Y>
        </Points>
        <Points>
          <X>148.875</X>
          <Y>220.25</Y>
        </Points>
        <Points>
          <X>148.625</X>
          <Y>220.5</Y>
        </Points>
        <Points>
          <X>148.625</X>
          <Y>220.5</Y>
        </Points>
        <Points>
          <X>148.5</X>
          <Y>221</Y>
        </Points>
        <Forces>14:32:4A:52:00:</Forces>
      </Stroke>
      <Stroke>
        <StrokeIdx>57</StrokeIdx>
        <ID>57</ID>
        <StartDate>2004-10-28T09:16:30.0000000+01:00</StartDate>
        <StartMs>-180</StartMs>
        <Duration>600</Duration>
        <Color>-14090101</Color>
        <Width>1</Width>
        <Points>
          <X>150.75</X>
          <Y>221.125</Y>
        </Points>
        <Points>
          <X>150.75</X>
          <Y>220.25</Y>
        </Points>
        <Points>
          <X>149.625</X>
          <Y>224.25</Y>
        </Points>
        <Points>
          <X>147.5</X>
          <Y>229.5</Y>
        </Points>
        <Points>
          <X>144.5</X>
          <Y>235.75</Y>
        </Points>
        <Points>
          <X>144.5</X>
          <Y>235.875</Y>
        </Points>
        <Points>
          <X>144.5</X>
          <Y>235.75</Y>
        </Points>
        <Points>
          <X>145.875</X>
          <Y>231.75</Y>
        </Points>
        <Points>
          <X>147.375</X>
          <Y>228.375</Y>
        </Points>
        <Points>
          <X>150.375</X>
          <Y>222.625</Y>
        </Points>
        <Points>
          <X>151</X>
          <Y>221</Y>
        </Points>
        <Points>
          <X>152.25</X>
          <Y>226.625</Y>
        </Points>
        <Points>
          <X>155.75</X>
          <Y>236</Y>
        </Points>
        <Points>
          <X>156.25</X>
          <Y>236.75</Y>
        </Points>
        <Points>
          <X>156.625</X>
          <Y>237.125</Y>
        </Points>
        <Points>
          <X>157.125</X>
          <Y>237</Y>
        </Points>
        <Points>
          <X>158</X>
          <Y>236.375</Y>
        </Points>
        <Points>
          <X>161.25</X>
          <Y>231.375</Y>
        </Points>
        <Points>
          <X>163.75</X>
          <Y>224.375</Y>
        </Points>
        <Points>
          <X>163.875</X>
          <Y>222.5</Y>
        </Points>
        <Points>
          <X>163.625</X>
          <Y>221.625</Y>
        </Points>
        <Forces>00:06:3E:48:4C:4A:40:00:00:00:24:3C:3E:3C:3E:48:52:5A:5A:56:0A:</Forces>
      </Stroke>
      <Stroke>
        <StrokeIdx>58</StrokeIdx>
        <ID>58</ID>
        <StartDate>2004-10-28T09:16:31.0000000+01:00</StartDate>
        <StartMs>-445</StartMs>
        <Duration>186</Duration>
        <Color>-14090101</Color>
        <Width>1</Width>
        <Points>
          <X>168.625</X>
          <Y>230.625</Y>
        </Points>
        <Points>
          <X>167.875</X>
          <Y>231.25</Y>
        </Points>
        <Points>
          <X>167.75</X>
          <Y>231.75</Y>
        </Points>
        <Points>
          <X>168</X>
          <Y>233.625</Y>
        </Points>
        <Points>
          <X>168.625</X>
          <Y>234.25</Y>
        </Points>
        <Points>
          <X>169.25</X>
          <Y>234.5</Y>
        </Points>
        <Points>
          <X>170.875</X>
          <Y>234.125</Y>
        </Points>
        <Points>
          <X>171.375</X>
          <Y>233.75</Y>
        </Points>
        <Points>
          <X>172.125</X>
          <Y>232.75</Y>
        </Points>
        <Points>
          <X>172.75</X>
          <Y>231</Y>
        </Points>
        <Points>
          <X>173.25</X>
          <Y>230.25</Y>
        </Points>
        <Forces>00:18:26:2E:30:34:44:4C:4E:30:00:</Forces>
      </Stroke>
      <Stroke>
        <StrokeIdx>59</StrokeIdx>
        <ID>59</ID>
        <StartDate>2004-10-28T09:16:31.0000000+01:00</StartDate>
        <StartMs>-175</StartMs>
        <Duration>1146</Duration>
        <Color>-14090101</Color>
        <Width>1</Width>
        <Points>
          <X>178.5</X>
          <Y>230.125</Y>
        </Points>
        <Points>
          <X>178.25</X>
          <Y>232.5</Y>
        </Points>
        <Points>
          <X>178.25</X>
          <Y>233.625</Y>
        </Points>
        <Points>
          <X>178.375</X>
          <Y>233.875</Y>
        </Points>
        <Points>
          <X>180.125</X>
          <Y>231.75</Y>
        </Points>
        <Points>
          <X>181.125</X>
          <Y>230.875</Y>
        </Points>
        <Points>
          <X>182.875</X>
          <Y>233.25</Y>
        </Points>
        <Points>
          <X>183.5</X>
          <Y>233.625</Y>
        </Points>
        <Points>
          <X>185.625</X>
          <Y>233.125</Y>
        </Points>
        <Points>
          <X>189</X>
          <Y>231</Y>
        </Points>
        <Points>
          <X>190.875</X>
          <Y>233</Y>
        </Points>
        <Points>
          <X>191.875</X>
          <Y>233.25</Y>
        </Points>
        <Points>
          <X>193</X>
          <Y>232.875</Y>
        </Points>
        <Points>
          <X>194.375</X>
          <Y>231.875</Y>
        </Points>
        <Points>
          <X>195.625</X>
          <Y>230.25</Y>
        </Points>
        <Points>
          <X>196.875</X>
          <Y>227.75</Y>
        </Points>
        <Points>
          <X>199.25</X>
          <Y>219.875</Y>
        </Points>
        <Points>
          <X>199.25</X>
          <Y>220</Y>
        </Points>
        <Points>
          <X>196.25</X>
          <Y>234.375</Y>
        </Points>
        <Points>
          <X>196.625</X>
          <Y>233.25</Y>
        </Points>
        <Points>
          <X>197.625</X>
          <Y>232</Y>
        </Points>
        <Points>
          <X>198.75</X>
          <Y>231.375</Y>
        </Points>
        <Points>
          <X>199.25</X>
          <Y>231.75</Y>
        </Points>
        <Points>
          <X>196.5</X>
          <Y>234</Y>
        </Points>
        <Points>
          <X>197.5</X>
          <Y>234.25</Y>
        </Points>
        <Points>
          <X>202.125</X>
          <Y>233.375</Y>
        </Points>
        <Points>
          <X>206.625</X>
          <Y>231.875</Y>
        </Points>
        <Points>
          <X>207.5</X>
          <Y>231.25</Y>
        </Points>
        <Points>
          <X>206.875</X>
          <Y>230.75</Y>
        </Points>
        <Points>
          <X>206.25</X>
          <Y>230.75</Y>
        </Points>
        <Points>
          <X>205.375</X>
          <Y>231.125</Y>
        </Points>
        <Points>
          <X>204.5</X>
          <Y>232.125</Y>
        </Points>
        <Points>
          <X>204.125</X>
          <Y>233.25</Y>
        </Points>
        <Points>
          <X>204.5</X>
          <Y>235.25</Y>
        </Points>
        <Points>
          <X>205</X>
          <Y>235.875</Y>
        </Points>
        <Points>
          <X>208</X>
          <Y>235.5</Y>
        </Points>
        <Points>
          <X>210</X>
          <Y>234.5</Y>
        </Points>
        <Points>
          <X>213</X>
          <Y>231.75</Y>
        </Points>
        <Points>
          <X>213</X>
          <Y>231.875</Y>
        </Points>
        <Points>
          <X>213.375</X>
          <Y>233.25</Y>
        </Points>
        <Points>
          <X>215.125</X>
          <Y>234.5</Y>
        </Points>
        <Forces>00:2E:34:34:42:44:46:46:48:50:42:3E:3E:3E:40:46:5A:5C:58:58:48:42:2C:40:34:2A:24:28:46:4A:4C:4C:48:38:30:38:3A:5A:5A:3E:16:</Forces>
      </Stroke>
      <Stroke>
        <StrokeIdx>60</StrokeIdx>
        <ID>60</ID>
        <StartDate>2004-10-28T09:16:32.0000000+01:00</StartDate>
        <StartMs>219</StartMs>
        <Duration>293</Duration>
        <Color>-14090101</Color>
        <Width>1</Width>
        <Points>
          <X>263.25</X>
          <Y>222.875</Y>
        </Points>
        <Points>
          <X>262.875</X>
          <Y>222.75</Y>
        </Points>
        <Points>
          <X>262.75</X>
          <Y>223.375</Y>
        </Points>
        <Points>
          <X>260.875</X>
          <Y>235.75</Y>
        </Points>
        <Points>
          <X>261.25</X>
          <Y>234.75</Y>
        </Points>
        <Points>
          <X>262.25</X>
          <Y>233.5</Y>
        </Points>
        <Points>
          <X>264.25</X>
          <Y>232.5</Y>
        </Points>
        <Points>
          <X>266.375</X>
          <Y>232.375</Y>
        </Points>
        <Points>
          <X>267.5</X>
          <Y>232.75</Y>
        </Points>
        <Points>
          <X>267.75</X>
          <Y>233.5</Y>
        </Points>
        <Points>
          <X>267.375</X>
          <Y>234.5</Y>
        </Points>
        <Points>
          <X>265</X>
          <Y>236.125</Y>
        </Points>
        <Points>
          <X>263.625</X>
          <Y>236.5</Y>
        </Points>
        <Points>
          <X>263</X>
          <Y>236.625</Y>
        </Points>
        <Points>
          <X>263.125</X>
          <Y>236.5</Y>
        </Points>
        <Forces>00:34:32:46:4E:44:3C:38:34:30:34:3C:3C:28:00:</Forces>
      </Stroke>
      <Stroke>
        <StrokeIdx>61</StrokeIdx>
        <ID>61</ID>
        <StartDate>2004-10-28T09:16:33.0000000+01:00</StartDate>
        <StartMs>-404</StartMs>
        <Duration>133</Duration>
        <Color>-14090101</Color>
        <Width>1</Width>
        <Points>
          <X>274.375</X>
          <Y>232.625</Y>
        </Points>
        <Points>
          <X>273.75</X>
          <Y>233.5</Y>
        </Points>
        <Points>
          <X>273.5</X>
          <Y>234.25</Y>
        </Points>
        <Points>
          <X>274.125</X>
          <Y>236.25</Y>
        </Points>
        <Points>
          <X>275</X>
          <Y>236.875</Y>
        </Points>
        <Points>
          <X>277</X>
          <Y>236.625</Y>
        </Points>
        <Points>
          <X>278.125</X>
          <Y>235.875</Y>
        </Points>
        <Points>
          <X>279.375</X>
          <Y>234.625</Y>
        </Points>
        <Forces>00:22:2A:3A:40:44:32:00:</Forces>
      </Stroke>
      <Stroke>
        <StrokeIdx>62</StrokeIdx>
        <ID>62</ID>
        <StartDate>2004-10-28T09:16:33.0000000+01:00</StartDate>
        <StartMs>-185</StartMs>
        <Duration>106</Duration>
        <Color>-14090101</Color>
        <Width>1</Width>
        <Points>
          <X>287.875</X>
          <Y>225</Y>
        </Points>
        <Points>
          <X>287.625</X>
          <Y>224.75</Y>
        </Points>
        <Points>
          <X>287.625</X>
          <Y>225.25</Y>
        </Points>
        <Points>
          <X>286.375</X>
          <Y>233.375</Y>
        </Points>
        <Points>
          <X>285.875</X>
          <Y>235.75</Y>
        </Points>
        <Forces>00:4E:56:50:20:</Forces>
      </Stroke>
      <Stroke>
        <StrokeIdx>63</StrokeIdx>
        <ID>63</ID>
        <StartDate>2004-10-28T09:16:33.0000000+01:00</StartDate>
        <StartMs>32</StartMs>
        <Duration>80</Duration>
        <Color>-14090101</Color>
        <Width>1</Width>
        <Points>
          <X>294.25</X>
          <Y>226.875</Y>
        </Points>
        <Points>
          <X>293.875</X>
          <Y>226.5</Y>
        </Points>
        <Points>
          <X>293.75</X>
          <Y>228.25</Y>
        </Points>
        <Points>
          <X>293.5</X>
          <Y>233.5</Y>
        </Points>
        <Points>
          <X>293.375</X>
          <Y>235.875</Y>
        </Points>
        <Forces>00:2E:42:30:00:</Forces>
      </Stroke>
      <Stroke>
        <StrokeIdx>64</StrokeIdx>
        <ID>64</ID>
        <StartDate>2004-10-28T09:16:33.0000000+01:00</StartDate>
        <StartMs>201</StartMs>
        <Duration>53</Duration>
        <Color>-14090101</Color>
        <Width>1</Width>
        <Points>
          <X>283.5</X>
          <Y>233</Y>
        </Points>
        <Points>
          <X>283.625</X>
          <Y>232</Y>
        </Points>
        <Points>
          <X>285.125</X>
          <Y>231.375</Y>
        </Points>
        <Points>
          <X>292.125</X>
          <Y>230.875</Y>
        </Points>
        <Forces>00:00:00:00:</Forces>
      </Stroke>
      <Stroke>
        <StrokeIdx>65</StrokeIdx>
        <ID>65</ID>
        <StartDate>2004-10-28T09:16:33.0000000+01:00</StartDate>
        <StartMs>276</StartMs>
        <Duration>226</Duration>
        <Color>-14090101</Color>
        <Width>1</Width>
        <Points>
          <X>297.375</X>
          <Y>230.875</Y>
        </Points>
        <Points>
          <X>301.375</X>
          <Y>231.125</Y>
        </Points>
        <Points>
          <X>301.25</X>
          <Y>231.25</Y>
        </Points>
        <Points>
          <X>298.5</X>
          <Y>232.75</Y>
        </Points>
        <Points>
          <X>297.375</X>
          <Y>235</Y>
        </Points>
        <Points>
          <X>297.625</X>
          <Y>236</Y>
        </Points>
        <Points>
          <X>298.25</X>
          <Y>236.75</Y>
        </Points>
        <Points>
          <X>299.125</X>
          <Y>236.875</Y>
        </Points>
        <Points>
          <X>300.5</X>
          <Y>236.625</Y>
        </Points>
        <Points>
          <X>301.75</X>
          <Y>235.875</Y>
        </Points>
        <Points>
          <X>302.625</X>
          <Y>233.875</Y>
        </Points>
        <Points>
          <X>302.25</X>
          <Y>231.875</Y>
        </Points>
        <Forces>00:00:00:36:38:2C:26:26:34:3A:48:1A:</Forces>
      </Stroke>
      <Stroke>
        <StrokeIdx>66</StrokeIdx>
        <ID>66</ID>
        <StartDate>2004-10-28T09:16:34.0000000+01:00</StartDate>
        <StartMs>-405</StartMs>
        <Duration>666</Duration>
        <Color>-14090101</Color>
        <Width>1</Width>
        <Points>
          <X>308</X>
          <Y>232</Y>
        </Points>
        <Points>
          <X>308.125</X>
          <Y>232.375</Y>
        </Points>
        <Points>
          <X>308.25</X>
          <Y>232.875</Y>
        </Points>
        <Points>
          <X>308.25</X>
          <Y>234.5</Y>
        </Points>
        <Points>
          <X>308.125</X>
          <Y>235.25</Y>
        </Points>
        <Points>
          <X>308.125</X>
          <Y>235.625</Y>
        </Points>
        <Points>
          <X>308.125</X>
          <Y>235.75</Y>
        </Points>
        <Points>
          <X>308.875</X>
          <Y>233.75</Y>
        </Points>
        <Points>
          <X>310.625</X>
          <Y>232.125</Y>
        </Points>
        <Points>
          <X>312.25</X>
          <Y>231.125</Y>
        </Points>
        <Points>
          <X>313.25</X>
          <Y>230.75</Y>
        </Points>
        <Points>
          <X>314.5</X>
          <Y>235</Y>
        </Points>
        <Points>
          <X>316.75</X>
          <Y>234.75</Y>
        </Points>
        <Points>
          <X>320</X>
          <Y>232.25</Y>
        </Points>
        <Points>
          <X>321.375</X>
          <Y>229.5</Y>
        </Points>
        <Points>
          <X>321.5</X>
          <Y>228</Y>
        </Points>
        <Points>
          <X>320.75</X>
          <Y>227.5</Y>
        </Points>
        <Points>
          <X>320</X>
          <Y>228.25</Y>
        </Points>
        <Points>
          <X>319.75</X>
          <Y>229.375</Y>
        </Points>
        <Points>
          <X>320</X>
          <Y>230.875</Y>
        </Points>
        <Points>
          <X>322.625</X>
          <Y>235.375</Y>
        </Points>
        <Points>
          <X>320.5</X>
          <Y>235.625</Y>
        </Points>
        <Points>
          <X>320</X>
          <Y>235.5</Y>
        </Points>
        <Points>
          <X>319.25</X>
          <Y>235.5</Y>
        </Points>
        <Forces>00:00:32:46:48:4A:4A:56:56:54:54:4C:4E:58:5E:66:66:60:5E:5E:5E:64:5C:00:</Forces>
      </Stroke>
      <Stroke>
        <StrokeIdx>67</StrokeIdx>
        <ID>67</ID>
        <StartDate>2004-10-28T09:16:34.0000000+01:00</StartDate>
        <StartMs>495</StartMs>
        <Duration>146</Duration>
        <Color>-14090101</Color>
        <Width>1</Width>
        <Points>
          <X>331.375</X>
          <Y>235.875</Y>
        </Points>
        <Points>
          <X>332.125</X>
          <Y>236.75</Y>
        </Points>
        <Points>
          <X>332.125</X>
          <Y>236.875</Y>
        </Points>
        <Points>
          <X>332.25</X>
          <Y>236.875</Y>
        </Points>
        <Points>
          <X>332.25</X>
          <Y>236.875</Y>
        </Points>
        <Points>
          <X>332.25</X>
          <Y>237</Y>
        </Points>
        <Points>
          <X>332.25</X>
          <Y>237</Y>
        </Points>
        <Points>
          <X>332.25</X>
          <Y>236.875</Y>
        </Points>
        <Points>
          <X>332.25</X>
          <Y>236.75</Y>
        </Points>
        <Points>
          <X>331.75</X>
          <Y>236.5</Y>
        </Points>
        <Forces>00:6A:76:7C:7E:7E:7E:7E:70:00:</Forces>
      </Stroke>
    </Layer>
  </Document>
</Info>